Workbook

Sheet 📋 Instrucciones
A1: PIL Perú — Base de datos de Marketing Digital
A3: RESUMEN DEL ARCHIVO
A5: Hoja | B5: Contenido
A6: 📋 Instrucciones | B6: Esta hoja — guía de uso del archivo
A7: 📘 Facebook_KPIs | B7: Métricas mensuales de Facebook (seguidores, alcance, interacciones, posts)
A8: 💼 LinkedIn_KPIs | B8: Métricas mensuales de LinkedIn (seguidores, alcance, impresiones, interacciones)
A9: 🌐 Web_Visitas | B9: Tráfico mensual del sitio web pil.com.pe — histórico 2021 a la fecha
A10: 🔍 GSC_SearchConsole | B10: Datos mensuales de Google Search Console (clics, impresiones, CTR)
A11: 📊 GA4_Analytics | B11: Datos mensuales de Google Analytics 4 (usuarios, canales, eventos)
A12: 🔑 GSC_Keywords | B12: Top keywords por mes (consultas de búsqueda orgánica)
A13: 📈 Resumen_Ejecutivo | B13: KPIs consolidados automáticos — para copiar a reportes y AppSheet
A15: 📅 Grilla_Contenidos | B15: Calendario editorial completo 2026 — publicaciones planificadas por fecha, categoría, formato y red social
A16: 📊 Grilla_Resumen | B16: Distribución de publicaciones 2026 por categoría (totales y porcentajes)
A17: 📆 Grilla_Vista_Mes | B17: Vista consolidada de publicaciones por mes y categoría — totales mensuales
A19: INSTRUCCIONES DE USO
A21: 1 | B21: Cada mes, ingresa los datos en las hojas correspondientes (Facebook, LinkedIn, Web, GSC, GA4).
A22: 2 | B22: Los campos en AZUL son ingreso manual. Los campos en VERDE calculan automáticamente.
A23: 3 | B23: La hoja 'Resumen_Ejecutivo' consolida todo automáticamente — no la edites manualmente.
A24: 4 | B24: AppSheet leerá la hoja 'Resumen_Ejecutivo' para mostrar los KPIs en la app.
A25: 5 | B25: No elimines filas ni columnas — AppSheet depende de la estructura fija.
A26: 6 | B26: Las hojas de Grilla (📅 Grilla_Contenidos, 📊 Grilla_Resumen, 📆 Grilla_Vista_Mes) son de planeación editorial. Actualiza el Estado de cada publicación (Pendiente → Publicado) conforme avance la ejecución.
A28: CONVENCIÓN DE COLORES
A30: Fondo AZUL claro | B30: Dato de ingreso manual — ingresa aquí cada mes
A31: Fondo VERDE claro | B31: Fórmula automática — no editar
A32: Fondo GRIS | B32: Dato no aplica o período sin datos aún
A34: Última actualización: | B34: Abril 2026 — Brian Reque Aradiel

Sheet 📅 Grilla_Contenidos
A1: PIL PERÚ SAC – GRILLA DE CONTENIDOS REDES SOCIALES 2026
A2: N° | B2: Fecha | C2: Día | D2: Semana | E2: Mes | F2: Categoría | G2: Tema / Contenido | H2: Formato | I2: Red Social | J2: Estado | K2: Responsable | L2: Observaciones
A3: ── MAYO ──
A4: 1 | B4: 2026-05-04 | C4: Lunes | D4: Sem 1 | E4: Mayo | F4: Efeméride | G4: 📅 Día de la Madre – Saludamos a todas las madres de PIL Perú | H4: Imagen + Copy | I4: LinkedIn / Facebook | J4: Pendiente
A5: 2 | B5: 2026-05-06 | C5: Miércoles | D5: Sem 1 | E5: Mayo | F5: Actividad PIL | G5: Capacitación interna: Seguridad eléctrica en campo | H5: Foto + Copy | I5: LinkedIn / Facebook | J5: Pendiente
A6: 3 | B6: 2026-05-08 | C6: Viernes | D6: Sem 1 | E6: Mayo | F6: Proyecto/Servicio | G6: Proyecto destacado: Automatización de tableros en planta minera – resultados alcanzados | H6: Carrusel de imágenes | I6: LinkedIn / Facebook | J6: Pendiente
A7: 4 | B7: 2026-05-11 | C7: Lunes | D7: Sem 2 | E7: Mayo | F7: Efeméride | G7: 📅 Día Internacional de los Trabajadores de la Salud | H7: Imagen + Copy | I7: LinkedIn / Facebook | J7: Pendiente
A8: 5 | B8: 2026-05-13 | C8: Miércoles | D8: Sem 2 | E8: Mayo | F8: Actividad PIL | G8: Visita técnica a cliente del sector oil & gas – reforzando lazos comerciales | H8: Foto + Copy | I8: LinkedIn / Facebook | J8: Pendiente
A9: 6 | B9: 2026-05-15 | C9: Viernes | D9: Sem 2 | E9: Mayo | F9: Proyecto/Servicio | G9: Servicio de ingeniería eléctrica industrial: ¿qué incluye y cómo contratarlo? | H9: Carrusel / Flyer | I9: LinkedIn / Facebook | J9: Pendiente
A10: 7 | B10: 2026-05-18 | C10: Lunes | D10: Sem 3 | E10: Mayo | F10: Noticia Web | G10: Telecomunicaciones industriales: cómo integrarlas a tus sistemas de control | H10: Imagen + Link al artículo | I10: LinkedIn / Facebook | J10: Pendiente
A11: 8 | B11: 2026-05-20 | C11: Miércoles | D11: Sem 3 | E11: Mayo | F11: Actividad PIL | G11: Charla interna: Tendencias en automatización industrial 2026 | H11: Foto + Copy | I11: LinkedIn / Facebook | J11: Pendiente
A12: 9 | B12: 2026-05-22 | C12: Viernes | D12: Sem 3 | E12: Mayo | F12: Proyecto/Servicio | G12: Caso de éxito: Instalación de sistema SCADA en planta de procesamiento | H12: Galería / Infografía | I12: LinkedIn / Facebook | J12: Pendiente
A13: 10 | B13: 2026-05-25 | C13: Lunes | D13: Sem 4 | E13: Mayo | F13: Efeméride | G13: 📅 Día de la Educación Técnica – PIL Perú y el valor del conocimiento técnico | H13: Imagen + Copy | I13: LinkedIn / Facebook | J13: Pendiente
A14: 11 | B14: 2026-05-27 | C14: Miércoles | D14: Sem 4 | E14: Mayo | F14: Actividad PIL | G14: Evento de integración de equipos PIL – trabajo en campo y cultura corporativa | H14: Foto + Copy | I14: LinkedIn / Facebook | J14: Pendiente
A15: 12 | B15: 2026-05-29 | C15: Viernes | D15: Sem 4 | E15: Mayo | F15: Proyecto/Servicio | G15: Promoción: Asesoría en instrumentación y control – conoce nuestro alcance de servicio | H15: Carrusel / Flyer | I15: LinkedIn / Facebook | J15: Pendiente
A16: ── JUNIO ──
A17: 13 | B17: 2026-06-01 | C17: Lunes | D17: Sem 1 | E17: Junio | F17: Actividad PIL | G17: Capacitación técnica: Protocolos de comunicación industrial (Modbus, Profibus, Ethernet IP) | H17: Foto + Copy | I17: LinkedIn / Facebook | J17: Pendiente
A18: 14 | B18: 2026-06-03 | C18: Miércoles | D18: Sem 1 | E18: Junio | F18: Noticia Web | G18: ¿Cuánto cuesta un proyecto de automatización industrial en Perú? | H18: Imagen + Link al artículo | I18: LinkedIn / Facebook | J18: Pendiente
A19: 15 | B19: 2026-06-05 | C19: Viernes | D19: Sem 1 | E19: Junio | F19: Efeméride | G19: 📅 Día Mundial del Medio Ambiente – Ingeniería sostenible desde PIL Perú | H19: Imagen + Copy | I19: LinkedIn / Facebook | J19: Pendiente
A20: 16 | B20: 2026-06-08 | C20: Lunes | D20: Sem 2 | E20: Junio | F20: Proyecto/Servicio | G20: Proyecto: Instalación de tableros de control en complejo industrial – Lima | H20: Carrusel de imágenes | I20: LinkedIn / Facebook | J20: Pendiente
A21: 17 | B21: 2026-06-10 | C21: Miércoles | D21: Sem 2 | E21: Junio | F21: Actividad PIL | G21: Visita a obra: Supervisión de avance en proyecto EPC sector minero | H21: Foto + Copy | I21: LinkedIn / Facebook | J21: Pendiente
A22: 18 | B22: 2026-06-12 | C22: Viernes | D22: Sem 2 | E22: Junio | F22: Proyecto/Servicio | G22: Soluciones llave en mano PIL: desde el diseño hasta la puesta en marcha | H22: Carrusel / Flyer | I22: LinkedIn / Facebook | J22: Pendiente
A23: 19 | B23: 2026-06-15 | C23: Lunes | D23: Sem 3 | E23: Junio | F23: Noticia Web | G23: Tableros eléctricos industriales: qué especificaciones pedir antes de fabricar | H23: Imagen + Link al artículo | I23: LinkedIn / Facebook | J23: Pendiente
A24: 20 | B24: 2026-06-17 | C24: Miércoles | D24: Sem 3 | E24: Junio | F24: Efeméride | G24: 📅 Día del Padre – Reconocemos a los padres del equipo PIL Perú | H24: Imagen + Copy | I24: LinkedIn / Facebook | J24: Pendiente
A25: 21 | B25: 2026-06-19 | C25: Viernes | D25: Sem 3 | E25: Junio | F25: Actividad PIL | G25: Reunión de liderazgo PIL 2026: planificación estratégica del segundo semestre | H25: Foto + Copy | I25: LinkedIn / Facebook | J25: Pendiente
A26: 22 | B26: 2026-06-22 | C26: Lunes | D26: Sem 4 | E26: Junio | F26: Noticia Web | G26: ¿Qué es un proyecto llave en mano y cuándo conviene para la industria? | H26: Imagen + Link al artículo | I26: LinkedIn / Facebook | J26: Pendiente
A27: 23 | B27: 2026-06-24 | C27: Miércoles | D27: Sem 4 | E27: Junio | F27: Efeméride | G27: 📅 Inti Raymi – Celebramos nuestra identidad cultural peruana | H27: Imagen + Copy | I27: LinkedIn / Facebook | J27: Pendiente
A28: 24 | B28: 2026-06-26 | C28: Viernes | D28: Sem 4 | E28: Junio | F28: Noticia Web | G28: Proyectos EPC en minería: errores al contratar un proveedor | H28: Imagen + Link al artículo | I28: LinkedIn / Facebook | J28: Pendiente
A29: 25 | B29: 2026-06-29 | C29: Lunes | D29: Sem 5 | E29: Junio | F29: Efeméride | G29: 📅 San Pedro y San Pablo – Festividad nacional | H29: Imagen + Copy | I29: LinkedIn / Facebook | J29: Pendiente
A30: ── JULIO ──
A31: 26 | B31: 2026-07-01 | C31: Miércoles | D31: Sem 1 | E31: Julio | F31: Proyecto/Servicio | G31: Caso de éxito: Proyecto de automatización completado en planta concentradora | H31: Galería / Infografía | I31: LinkedIn / Facebook | J31: Pendiente
A32: 27 | B32: 2026-07-03 | C32: Viernes | D32: Sem 1 | E32: Julio | F32: Actividad PIL | G32: Capacitación: Seguridad en trabajos eléctricos bajo norma NFPA 70E | H32: Foto + Copy | I32: LinkedIn / Facebook | J32: Pendiente
A33: 28 | B33: 2026-07-06 | C33: Lunes | D33: Sem 2 | E33: Julio | F33: Noticia Web | G33: Instrumentación y control en plantas de gas y petróleo: guía práctica | H33: Imagen + Link al artículo | I33: LinkedIn / Facebook | J33: Pendiente
A34: 29 | B34: 2026-07-07 | C34: Martes | D34: Sem 2 | E34: Julio | F34: Noticia Web | G34: SCADA en la industria peruana: qué evaluar antes de implementarlo | H34: Imagen + Link al artículo | I34: LinkedIn / Facebook | J34: Pendiente
A35: 30 | B35: 2026-07-08 | C35: Miércoles | D35: Sem 2 | E35: Julio | F35: Actividad PIL | G35: Visita técnica a cliente: evaluación de necesidades en infraestructura industrial | H35: Foto + Copy | I35: LinkedIn / Facebook | J35: Pendiente
A36: 31 | B36: 2026-07-10 | C36: Viernes | D36: Sem 2 | E36: Julio | F36: Efeméride | G36: 📅 Semana Previa a Fiestas Patrias – PIL Perú: ingeniería con orgullo peruano | H36: Imagen + Copy | I36: LinkedIn / Facebook | J36: Pendiente
A37: 32 | B37: 2026-07-13 | C37: Lunes | D37: Sem 3 | E37: Julio | F37: Proyecto/Servicio | G37: Portafolio de servicios PIL: Ingeniería eléctrica, automatización y telecomunicaciones | H37: Carrusel / Flyer | I37: LinkedIn / Facebook | J37: Pendiente
A38: 33 | B38: 2026-07-20 | C38: Lunes | D38: Sem 4 | E38: Julio | F38: Noticia Web | G38: Ingeniería eléctrica industrial: cómo elegir al proveedor correcto | H38: Imagen + Link al artículo | I38: LinkedIn / Facebook | J38: Pendiente
A39: 34 | B39: 2026-07-22 | C39: Miércoles | D39: Sem 4 | E39: Julio | F39: Actividad PIL | G39: Evento interno PIL: Reconocimiento a colaboradores destacados del primer semestre | H39: Foto + Copy | I39: LinkedIn / Facebook | J39: Pendiente
A40: 35 | B40: 2026-07-24 | C40: Viernes | D40: Sem 4 | E40: Julio | F40: Efeméride | G40: 📅 Fiestas Patrias – PIL Perú celebra el 205° aniversario de la independencia del Perú | H40: Imagen + Copy | I40: LinkedIn / Facebook | J40: Pendiente
A41: 36 | B41: 2026-07-27 | C41: Lunes | D41: Sem 5 | E41: Julio | F41: Noticia Web | G41: Construcciones industriales llave en mano: qué incluye y qué no | H41: Imagen + Link al artículo | I41: LinkedIn / Facebook | J41: Pendiente
A42: 37 | B42: 2026-07-29 | C42: Miércoles | D42: Sem 5 | E42: Julio | F42: Proyecto/Servicio | G42: Nuevo contrato adjudicado: Proyecto de instrumentación en planta de gas natural | H42: Carrusel de imágenes | I42: LinkedIn / Facebook | J42: Pendiente
A43: 38 | B43: 2026-07-31 | C43: Viernes | D43: Sem 5 | E43: Julio | F43: Actividad PIL | G43: Cierre de mes: balance de proyectos ejecutados en julio 2026 | H43: Foto + Copy | I43: LinkedIn / Facebook | J43: Pendiente
A44: ── AGOSTO ──
A45: 39 | B45: 2026-08-03 | C45: Lunes | D45: Sem 1 | E45: Agosto | F45: Noticia Web | G45: Automatización en minería: beneficios reales y casos de uso en Perú | H45: Imagen + Link al artículo | I45: LinkedIn / Facebook | J45: Pendiente
A46: 40 | B46: 2026-08-05 | C46: Miércoles | D46: Sem 1 | E46: Agosto | F46: Actividad PIL | G46: Capacitación: Mantenimiento preventivo de sistemas de control industrial | H46: Foto + Copy | I46: LinkedIn / Facebook | J46: Pendiente
A47: 41 | B47: 2026-08-07 | C47: Viernes | D47: Sem 1 | E47: Agosto | F47: Proyecto/Servicio | G47: Proyecto ejecutado: Modernización de sistema eléctrico en planta industrial – Lima | H47: Galería / Infografía | I47: LinkedIn / Facebook | J47: Pendiente
A48: 42 | B48: 2026-08-10 | C48: Lunes | D48: Sem 2 | E48: Agosto | F48: Efeméride | G48: 📅 Día Internacional de los Pueblos Indígenas – PIL Perú y la industria responsable | H48: Imagen + Copy | I48: LinkedIn / Facebook | J48: Pendiente
A49: 43 | B49: 2026-08-12 | C49: Miércoles | D49: Sem 2 | E49: Agosto | F49: Actividad PIL | G49: Visita a proyecto en ejecución: supervisión de montaje de tableros industriales | H49: Foto + Copy | I49: LinkedIn / Facebook | J49: Pendiente
A50: 44 | B50: 2026-08-14 | C50: Viernes | D50: Sem 2 | E50: Agosto | F50: Proyecto/Servicio | G50: Servicio destacado: Soporte técnico y mantenimiento eléctrico industrial 24/7 | H50: Carrusel / Flyer | I50: LinkedIn / Facebook | J50: Pendiente
A51: 45 | B51: 2026-08-17 | C51: Lunes | D51: Sem 3 | E51: Agosto | F51: Noticia Web | G51: ¿Cuándo tercerizar el mantenimiento eléctrico industrial en tu planta? | H51: Imagen + Link al artículo | I51: LinkedIn / Facebook | J51: Pendiente
A52: 46 | B52: 2026-08-19 | C52: Miércoles | D52: Sem 3 | E52: Agosto | F52: Actividad PIL | G52: Evento de integración PIL: confraternidad y cultura de equipo | H52: Foto + Copy | I52: LinkedIn / Facebook | J52: Pendiente
A53: 47 | B53: 2026-08-21 | C53: Viernes | D53: Sem 3 | E53: Agosto | F53: Proyecto/Servicio | G53: Caso de éxito: Implementación de red de telecomunicaciones en complejo minero | H53: Galería / Infografía | I53: LinkedIn / Facebook | J53: Pendiente
A54: 48 | B54: 2026-08-24 | C54: Lunes | D54: Sem 4 | E54: Agosto | F54: Efeméride | G54: 📅 Día de la Bandera Peruana – PIL Perú: ingeniería hecha con orgullo nacional | H54: Imagen + Copy | I54: LinkedIn / Facebook | J54: Pendiente
A55: 49 | B55: 2026-08-26 | C55: Miércoles | D55: Sem 4 | E55: Agosto | F55: Actividad PIL | G55: Capacitación externa: normas IEC en sistemas de control y automatización | H55: Foto + Copy | I55: LinkedIn / Facebook | J55: Pendiente
A56: 50 | B56: 2026-08-28 | C56: Viernes | D56: Sem 4 | E56: Agosto | F56: Proyecto/Servicio | G56: Servicios PIL: Construcciones industriales bajo estándar EPC – ¿qué significa para ti? | H56: Carrusel / Flyer | I56: LinkedIn / Facebook | J56: Pendiente
A57: ── SEPTIEMBRE ──
A58: 51 | B58: 2026-09-02 | C58: Miércoles | D58: Sem 1 | E58: Septiembre | F58: Actividad PIL | G58: Capacitación interna: Gestión de proyectos bajo metodología PMI | H58: Foto + Copy | I58: LinkedIn / Facebook | J58: Pendiente
A59: 52 | B59: 2026-09-04 | C59: Viernes | D59: Sem 1 | E59: Septiembre | F59: Proyecto/Servicio | G59: Proyecto destacado: Automatización de subestación eléctrica en sector industrial | H59: Galería / Infografía | I59: LinkedIn / Facebook | J59: Pendiente
A60: 53 | B60: 2026-09-07 | C60: Lunes | D60: Sem 2 | E60: Septiembre | F60: Efeméride | G60: 📅 Día del Ingeniero Peruano – PIL Perú reconoce el talento técnico nacional | H60: Imagen + Copy | I60: LinkedIn / Facebook | J60: Pendiente
A61: 54 | B61: 2026-09-09 | C61: Miércoles | D61: Sem 2 | E61: Septiembre | F61: Actividad PIL | G61: Visita técnica a cliente: evaluación de sistemas SCADA existentes para upgrade | H61: Foto + Copy | I61: LinkedIn / Facebook | J61: Pendiente
A62: 55 | B62: 2026-09-11 | C62: Viernes | D62: Sem 2 | E62: Septiembre | F62: Proyecto/Servicio | G62: Servicio: Ingeniería de detalle para proyectos de instrumentación y control | H62: Carrusel / Flyer | I62: LinkedIn / Facebook | J62: Pendiente
A63: 56 | B63: 2026-09-14 | C63: Lunes | D63: Sem 3 | E63: Septiembre | F63: Efeméride | G63: 📅 Semana de la Prevención de Accidentes – Seguridad primero en PIL Perú | H63: Imagen + Copy | I63: LinkedIn / Facebook | J63: Pendiente
A64: 57 | B64: 2026-09-16 | C64: Miércoles | D64: Sem 3 | E64: Septiembre | F64: Actividad PIL | G64: Evento PIL: Seminario de actualización tecnológica para el equipo técnico | H64: Foto + Copy | I64: LinkedIn / Facebook | J64: Pendiente
A65: 58 | B65: 2026-09-18 | C65: Viernes | D65: Sem 3 | E65: Septiembre | F65: Proyecto/Servicio | G65: Caso de éxito: Proyecto llave en mano en planta de tratamiento de agua industrial | H65: Galería / Infografía | I65: LinkedIn / Facebook | J65: Pendiente
A66: 59 | B66: 2026-09-21 | C66: Lunes | D66: Sem 4 | E66: Septiembre | F66: Efeméride | G66: 📅 Día Internacional de la Paz – PIL Perú: construyendo con responsabilidad social | H66: Imagen + Copy | I66: LinkedIn / Facebook | J66: Pendiente
A67: 60 | B67: 2026-09-23 | C67: Miércoles | D67: Sem 4 | E67: Septiembre | F67: Actividad PIL | G67: Capacitación: Nuevas tecnologías en sistemas de telecomunicaciones industriales | H67: Foto + Copy | I67: LinkedIn / Facebook | J67: Pendiente
A68: 61 | B68: 2026-09-25 | C68: Viernes | D68: Sem 4 | E68: Septiembre | F68: Proyecto/Servicio | G68: Portafolio PIL: Proyectos en sectores minería, oil & gas e industria manufacturera | H68: Carrusel de imágenes | I68: LinkedIn / Facebook | J68: Pendiente
A69: 62 | B69: 2026-09-28 | C69: Lunes | D69: Sem 5 | E69: Septiembre | F69: Actividad PIL | G69: Balance del mes: logros, proyectos y aprendizajes del equipo PIL – Septiembre 2026 | H69: Foto + Copy | I69: LinkedIn / Facebook | J69: Pendiente
A70: ── OCTUBRE ──
A71: 63 | B71: 2026-10-02 | C71: Viernes | D71: Sem 1 | E71: Octubre | F71: Efeméride | G71: 📅 Día de los Animales – PIL Perú y el compromiso con el entorno | H71: Imagen + Copy | I71: LinkedIn / Facebook | J71: Pendiente
A72: 64 | B72: 2026-10-05 | C72: Lunes | D72: Sem 2 | E72: Octubre | F72: Proyecto/Servicio | G72: Proyecto ejecutado: Instalación de sistema de control PLC en planta de concentrados | H72: Galería / Infografía | I72: LinkedIn / Facebook | J72: Pendiente
A73: 65 | B73: 2026-10-07 | C73: Miércoles | D73: Sem 2 | E73: Octubre | F73: Efeméride | G73: 📅 Aniversario Batalla de Angamos – Orgullo peruano desde PIL Perú | H73: Imagen + Copy | I73: LinkedIn / Facebook | J73: Pendiente
A74: 66 | B74: 2026-10-09 | C74: Viernes | D74: Sem 2 | E74: Octubre | F74: Actividad PIL | G74: Capacitación: Fundamentos de redes industriales y ciberseguridad OT | H74: Foto + Copy | I74: LinkedIn / Facebook | J74: Pendiente
A75: 67 | B75: 2026-10-12 | C75: Lunes | D75: Sem 3 | E75: Octubre | F75: Proyecto/Servicio | G75: Servicio PIL: ¿Cómo abordamos un proyecto EPC desde la ingeniería básica? | H75: Carrusel / Flyer | I75: LinkedIn / Facebook | J75: Pendiente
A76: 68 | B76: 2026-10-14 | C76: Miércoles | D76: Sem 3 | E76: Octubre | F76: Actividad PIL | G76: Visita a proyecto: Supervisión de pruebas FAT en tableros de media tensión | H76: Foto + Copy | I76: LinkedIn / Facebook | J76: Pendiente
A77: 69 | B77: 2026-10-16 | C77: Viernes | D77: Sem 3 | E77: Octubre | F77: Efeméride | G77: 📅 Día Mundial de la Alimentación – PIL Perú en proyectos del sector agroindustrial | H77: Imagen + Copy | I77: LinkedIn / Facebook | J77: Pendiente
A78: 70 | B78: 2026-10-19 | C78: Lunes | D78: Sem 4 | E78: Octubre | F78: Proyecto/Servicio | G78: Nuevo proyecto adjudicado: Sistema de instrumentación en planta petroquímica | H78: Carrusel de imágenes | I78: LinkedIn / Facebook | J78: Pendiente
A79: 71 | B79: 2026-10-21 | C79: Miércoles | D79: Sem 4 | E79: Octubre | F79: Actividad PIL | G79: Evento: Participación de PIL Perú en feria de proveedores industriales | H79: Foto + Copy | I79: LinkedIn / Facebook | J79: Pendiente
A80: 72 | B80: 2026-10-23 | C80: Viernes | D80: Sem 4 | E80: Octubre | F80: Proyecto/Servicio | G80: Caso de éxito: Proyecto de telecomunicaciones en mina subterránea | H80: Galería / Infografía | I80: LinkedIn / Facebook | J80: Pendiente
A81: 73 | B81: 2026-10-28 | C81: Miércoles | D81: Sem 5 | E81: Octubre | F81: Actividad PIL | G81: Capacitación técnica: Actualización en normativas eléctricas CNE-Perú 2026 | H81: Foto + Copy | I81: LinkedIn / Facebook | J81: Pendiente
A82: 74 | B82: 2026-10-30 | C82: Viernes | D82: Sem 5 | E82: Octubre | F82: Efeméride | G82: 📅 Víspera de Todos los Santos – Mensaje corporativo de PIL Perú | H82: Imagen + Copy | I82: LinkedIn / Facebook | J82: Pendiente
A83: ── NOVIEMBRE ──
A84: 75 | B84: 2026-11-02 | C84: Lunes | D84: Sem 1 | E84: Noviembre | F84: Proyecto/Servicio | G84: Proyecto PIL: Instalación de sistema de videovigilancia industrial IP en planta minera | H84: Galería / Infografía | I84: LinkedIn / Facebook | J84: Pendiente
A85: 76 | B85: 2026-11-04 | C85: Miércoles | D85: Sem 1 | E85: Noviembre | F85: Actividad PIL | G85: Capacitación: Manejo seguro de equipos de alta tensión – equipo técnico PIL | H85: Foto + Copy | I85: LinkedIn / Facebook | J85: Pendiente
A86: 77 | B86: 2026-11-06 | C86: Viernes | D86: Sem 1 | E86: Noviembre | F86: Efeméride | G86: 📅 Semana de la Ciencia y Tecnología – PIL Perú: innovación al servicio de la industria | H86: Imagen + Copy | I86: LinkedIn / Facebook | J86: Pendiente
A87: 78 | B87: 2026-11-09 | C87: Lunes | D87: Sem 2 | E87: Noviembre | F87: Proyecto/Servicio | G87: Servicio: Auditoría de sistemas eléctricos industriales – previene antes que corregir | H87: Carrusel / Flyer | I87: LinkedIn / Facebook | J87: Pendiente
A88: 79 | B88: 2026-11-11 | C88: Miércoles | D88: Sem 2 | E88: Noviembre | F88: Actividad PIL | G88: Visita a obra: Avance del proyecto de automatización en complejo industrial costero | H88: Foto + Copy | I88: LinkedIn / Facebook | J88: Pendiente
A89: 80 | B89: 2026-11-13 | C89: Viernes | D89: Sem 2 | E89: Noviembre | F89: Efeméride | G89: 📅 Día de la Lealtad – Valores que guían al equipo PIL Perú | H89: Imagen + Copy | I89: LinkedIn / Facebook | J89: Pendiente
A90: 81 | B90: 2026-11-16 | C90: Lunes | D90: Sem 3 | E90: Noviembre | F90: Proyecto/Servicio | G90: Proyecto destacado: Red de fibra óptica industrial para complejo minero en Cusco | H90: Galería / Infografía | I90: LinkedIn / Facebook | J90: Pendiente
A91: 82 | B91: 2026-11-18 | C91: Miércoles | D91: Sem 3 | E91: Noviembre | F91: Actividad PIL | G91: Evento: Reunión anual de planificación estratégica PIL Perú 2027 | H91: Foto + Copy | I91: LinkedIn / Facebook | J91: Pendiente
A92: 83 | B92: 2026-11-20 | C92: Viernes | D92: Sem 3 | E92: Noviembre | F92: Efeméride | G92: 📅 Día Universal del Niño – PIL Perú con responsabilidad social empresarial | H92: Imagen + Copy | I92: LinkedIn / Facebook | J92: Pendiente
A93: 84 | B93: 2026-11-23 | C93: Lunes | D93: Sem 4 | E93: Noviembre | F93: Proyecto/Servicio | G93: Servicio PIL: Construcción de salas eléctricas bajo estándar IEC – casos ejecutados | H93: Carrusel de imágenes | I93: LinkedIn / Facebook | J93: Pendiente
A94: 85 | B94: 2026-11-25 | C94: Miércoles | D94: Sem 4 | E94: Noviembre | F94: Actividad PIL | G94: Capacitación final del año: Gestión de activos y confiabilidad industrial | H94: Foto + Copy | I94: LinkedIn / Facebook | J94: Pendiente
A95: 86 | B95: 2026-11-27 | C95: Viernes | D95: Sem 4 | E95: Noviembre | F95: Efeméride | G95: 📅 Día de la Solidaridad – PIL Perú: comprometidos con las comunidades donde operamos | H95: Imagen + Copy | I95: LinkedIn / Facebook | J95: Pendiente
A96: ── DICIEMBRE ──
A97: 87 | B97: 2026-12-02 | C97: Miércoles | D97: Sem 1 | E97: Diciembre | F97: Proyecto/Servicio | G97: Balance de proyectos 2026: lo que logramos este año en ingeniería e innovación | H97: Carrusel de imágenes | I97: LinkedIn / Facebook | J97: Pendiente
A98: 88 | B98: 2026-12-04 | C98: Viernes | D98: Sem 1 | E98: Diciembre | F98: Actividad PIL | G98: Evento de cierre de año PIL Perú: celebrando los logros del equipo | H98: Foto + Copy | I98: LinkedIn / Facebook | J98: Pendiente
A99: 89 | B99: 2026-12-07 | C99: Lunes | D99: Sem 2 | E99: Diciembre | F99: Efeméride | G99: 📅 Día de la Inmaculada Concepción – Mensaje de PIL Perú | H99: Imagen + Copy | I99: LinkedIn / Facebook | J99: Pendiente
A100: 90 | B100: 2026-12-09 | C100: Miércoles | D100: Sem 2 | E100: Diciembre | F100: Efeméride | G100: 📅 Batalla de Ayacucho – 202° aniversario de la independencia latinoamericana | H100: Imagen + Copy | I100: LinkedIn / Facebook | J100: Pendiente
...

Sheet 📊 Grilla_Resumen
A1: PIL PERÚ SAC – RESUMEN DE GRILLA DE CONTENIDOS 2026
A2: Período: Mayo – Diciembre 2026
A4: DISTRIBUCIÓN POR CATEGORÍA
A5: Categoría | B5: # Publicaciones | C5: % del Total | D5: Color
A6: Actividad PIL | B6: 33 | C6: 33.7%
A7: Proyecto/Servicio | B7: 28 | C7: 28.6%
A8: Efeméride | B8: 26 | C8: 26.5%
A9: Noticia Web | B9: 11 | C9: 11.2%
A10: TOTAL | B10: 98 | C10: 100%
A12: LEYENDA DE ESTADOS
A13: Pendiente
A14: En proceso
A15: Aprobado
A16: Publicado
A17: Cancelado

Sheet 📆 Grilla_Vista_Mes
A1: PUBLICACIONES POR MES – PIL PERÚ 2026
A2: Mes | B2: Noticia Web | C2: Efeméride | D2: Proyecto/Servicio | E2: Actividad PIL | F2: Contenido Corporativo | G2: Promoción de Servicio | H2: Total
A3: Mayo | B3: 1 | C3: 3 | D3: 4 | E3: 4 | F3: 0 | G3: 0 | H3: 12
A4: Junio | B4: 4 | C4: 4 | D4: 2 | E4: 3 | F4: 0 | G4: 0 | H4: 13
A5: Julio | B5: 4 | C5: 2 | D5: 3 | E5: 4 | F5: 0 | G5: 0 | H5: 13
A6: Agosto | B6: 2 | C6: 2 | D6: 4 | E6: 4 | F6: 0 | G6: 0 | H6: 12
A7: Septiembre | B7: 0 | C7: 3 | D7: 4 | E7: 5 | F7: 0 | G7: 0 | H7: 12
A8: Octubre | B8: 0 | C8: 4 | D8: 4 | E8: 4 | F8: 0 | G8: 0 | H8: 12
A9: Noviembre | B9: 0 | C9: 4 | D9: 4 | E9: 4 | F9: 0 | G9: 0 | H9: 12
A10: Diciembre | B10: 0 | C10: 4 | D10: 3 | E10: 5 | F10: 0 | G10: 0 | H10: 12
A11: TOTAL | B11: 11 | C11: 26 | D11: 28 | E11: 33 | F11: 0 | G11: 0 | H11: 98

Sheet 📘 Facebook_KPIs
A1: PIL Perú — KPIs Facebook
A2: Benchmark: Alcance ≥ 18% de seguidores | Interacción ≥ 7.5% — Azul = ingreso manual | Verde = fórmula automática
A3: Año | B3: Mes | C3: Seguidores Totales | D3: Impresiones | E3: Alcance | F3: Interacciones | G3: Nuevos Seguidores | H3: Posts Publicados | I3: % Alcance (Alc/Seg) | J3: % Interacción (Int/Alc) | K3: Estado Alcance | L3: Estado Interacción
A4: 2021 | B4: Enero | E4: 2366 | F4: 166 | G4: 20 | H4: 7 | J4: =IF(AND(E4<>"",F4<>""),F4/E4,"") -> 0.070160609 | K4: =IF(I4="","",IF(I4>=0.18,"✓ Cumple","✗ Por debajo")) | L4: =IF(J4="","",IF(J4>=0.075,"✓ Cumple","✗ Por debajo")) -> ✗ Por debajo
A5: 2021 | B5: Febrero | E5: 917 | F5: 49 | G5: 10 | H5: 1 | J5: =IF(AND(E5<>"",F5<>""),F5/E5,"") -> 0.053435115 | K5: =IF(I5="","",IF(I5>=0.18,"✓ Cumple","✗ Por debajo")) | L5: =IF(J5="","",IF(J5>=0.075,"✓ Cumple","✗ Por debajo")) -> ✗ Por debajo
A6: 2021 | B6: Marzo | E6: 2918 | F6: 258 | G6: 15 | H6: 5 | J6: =IF(AND(E6<>"",F6<>""),F6/E6,"") -> 0.088416724 | K6: =IF(I6="","",IF(I6>=0.18,"✓ Cumple","✗ Por debajo")) | L6: =IF(J6="","",IF(J6>=0.075,"✓ Cumple","✗ Por debajo")) -> ✓ Cumple
A7: 2021 | B7: Abril | E7: 10771 | F7: 618 | G7: 25 | H7: 9 | J7: =IF(AND(E7<>"",F7<>""),F7/E7,"") -> 0.057376288 | K7: =IF(I7="","",IF(I7>=0.18,"✓ Cumple","✗ Por debajo")) | L7: =IF(J7="","",IF(J7>=0.075,"✓ Cumple","✗ Por debajo")) -> ✗ Por debajo
A8: 2021 | B8: Mayo | E8: 7737 | F8: 633 | G8: 18 | H8: 11 | J8: =IF(AND(E8<>"",F8<>""),F8/E8,"") -> 0.081814657 | K8: =IF(I8="","",IF(I8>=0.18,"✓ Cumple","✗ Por debajo")) | L8: =IF(J8="","",IF(J8>=0.075,"✓ Cumple","✗ Por debajo")) -> ✓ Cumple
A9: 2021 | B9: Junio | E9: 6680 | F9: 536 | G9: 15 | H9: 11 | J9: =IF(AND(E9<>"",F9<>""),F9/E9,"") -> 0.080239521 | K9: =IF(I9="","",IF(I9>=0.18,"✓ Cumple","✗ Por debajo")) | L9: =IF(J9="","",IF(J9>=0.075,"✓ Cumple","✗ Por debajo")) -> ✓ Cumple
A10: 2021 | B10: Julio | E10: 2182 | F10: 125 | G10: 8 | H10: 3 | J10: =IF(AND(E10<>"",F10<>""),F10/E10,"") -> 0.057286893 | K10: =IF(I10="","",IF(I10>=0.18,"✓ Cumple","✗ Por debajo")) | L10: =IF(J10="","",IF(J10>=0.075,"✓ Cumple","✗ Por debajo")) -> ✗ Por debajo
A11: 2021 | B11: Agosto | E11: 782 | F11: 68 | G11: 5 | H11: 1 | J11: =IF(AND(E11<>"",F11<>""),F11/E11,"") -> 0.086956522 | K11: =IF(I11="","",IF(I11>=0.18,"✓ Cumple","✗ Por debajo")) | L11: =IF(J11="","",IF(J11>=0.075,"✓ Cumple","✗ Por debajo")) -> ✓ Cumple
A12: 2021 | B12: Setiembre | E12: 2302 | F12: 141 | G12: 8 | H12: 3 | J12: =IF(AND(E12<>"",F12<>""),F12/E12,"") -> 0.061251086 | K12: =IF(I12="","",IF(I12>=0.18,"✓ Cumple","✗ Por debajo")) | L12: =IF(J12="","",IF(J12>=0.075,"✓ Cumple","✗ Por debajo")) -> ✗ Por debajo
A13: 2021 | B13: Octubre | E13: 4109 | F13: 282 | G13: 12 | H13: 7 | J13: =IF(AND(E13<>"",F13<>""),F13/E13,"") -> 0.068629837 | K13: =IF(I13="","",IF(I13>=0.18,"✓ Cumple","✗ Por debajo")) | L13: =IF(J13="","",IF(J13>=0.075,"✓ Cumple","✗ Por debajo")) -> ✗ Por debajo
A14: 2021 | B14: Noviembre | E14: 1748 | F14: 122 | G14: 8 | H14: 5 | J14: =IF(AND(E14<>"",F14<>""),F14/E14,"") -> 0.06979405 | K14: =IF(I14="","",IF(I14>=0.18,"✓ Cumple","✗ Por debajo")) | L14: =IF(J14="","",IF(J14>=0.075,"✓ Cumple","✗ Por debajo")) -> ✗ Por debajo
A15: 2021 | B15: Diciembre | E15: 3016 | F15: 316 | G15: 10 | H15: 6 | J15: =IF(AND(E15<>"",F15<>""),F15/E15,"") -> 0.10477454 | K15: =IF(I15="","",IF(I15>=0.18,"✓ Cumple","✗ Por debajo")) | L15: =IF(J15="","",IF(J15>=0.075,"✓ Cumple","✗ Por debajo")) -> ✓ Cumple
A16: 2022 | B16: Enero | C16: 2571 | D16: 3344 | E16: 1203 | F16: 116 | G16: 33 | H16: 4 | I16: =IF(AND(C16<>"",E16<>""),E16/C16,"") -> 0.46791132 | J16: =IF(AND(E16<>"",F16<>""),F16/E16,"") -> 0.096425603 | K16: =IF(I16="","",IF(I16>=0.18,"✓ Cumple","✗ Por debajo")) -> ✓ Cumple | L16: =IF(J16="","",IF(J16>=0.075,"✓ Cumple","✗ Por debajo")) -> ✓ Cumple
A17: 2022 | B17: Febrero | C17: 2610 | D17: 4322 | E17: 647 | F17: 399 | G17: 39 | H17: 4 | I17: =IF(AND(C17<>"",E17<>""),E17/C17,"") -> 0.24789272 | J17: =IF(AND(E17<>"",F17<>""),F17/E17,"") -> 0.61669243 | K17: =IF(I17="","",IF(I17>=0.18,"✓ Cumple","✗ Por debajo")) -> ✓ Cumple | L17: =IF(J17="","",IF(J17>=0.075,"✓ Cumple","✗ Por debajo")) -> ✓ Cumple
A18: 2022 | B18: Marzo | C18: 2634 | D18: 3146 | E18: 1076 | F18: 154 | G18: 24 | H18: 4 | I18: =IF(AND(C18<>"",E18<>""),E18/C18,"") -> 0.40850418 | J18: =IF(AND(E18<>"",F18<>""),F18/E18,"") -> 0.14312268 | K18: =IF(I18="","",IF(I18>=0.18,"✓ Cumple","✗ Por debajo")) -> ✓ Cumple | L18: =IF(J18="","",IF(J18>=0.075,"✓ Cumple","✗ Por debajo")) -> ✓ Cumple
A19: 2022 | B19: Abril | C19: 2642 | D19: 3743 | E19: 390 | F19: 118 | G19: 8 | H19: 4 | I19: =IF(AND(C19<>"",E19<>""),E19/C19,"") -> 0.14761544 | J19: =IF(AND(E19<>"",F19<>""),F19/E19,"") -> 0.3025641 | K19: =IF(I19="","",IF(I19>=0.18,"✓ Cumple","✗ Por debajo")) -> ✗ Por debajo | L19: =IF(J19="","",IF(J19>=0.075,"✓ Cumple","✗ Por debajo")) -> ✓ Cumple
A20: 2022 | B20: Mayo | C20: 2671 | D20: 4084 | E20: 358 | F20: 161 | G20: 29 | H20: 5 | I20: =IF(AND(C20<>"",E20<>""),E20/C20,"") -> 0.1340322 | J20: =IF(AND(E20<>"",F20<>""),F20/E20,"") -> 0.44972067 | K20: =IF(I20="","",IF(I20>=0.18,"✓ Cumple","✗ Por debajo")) -> ✗ Por debajo | L20: =IF(J20="","",IF(J20>=0.075,"✓ Cumple","✗ Por debajo")) -> ✓ Cumple
A21: 2022 | B21: Junio | C21: 2692 | D21: 4748 | E21: 426 | F21: 297 | G21: 21 | H21: 6 | I21: =IF(AND(C21<>"",E21<>""),E21/C21,"") -> 0.15824666 | J21: =IF(AND(E21<>"",F21<>""),F21/E21,"") -> 0.6971831 | K21: =IF(I21="","",IF(I21>=0.18,"✓ Cumple","✗ Por debajo")) -> ✗ Por debajo | L21: =IF(J21="","",IF(J21>=0.075,"✓ Cumple","✗ Por debajo")) -> ✓ Cumple
A22: 2022 | B22: Julio | C22: 2705 | D22: 3942 | E22: 771 | F22: 297 | G22: 13 | H22: 3 | I22: =IF(AND(C22<>"",E22<>""),E22/C22,"") -> 0.28502773 | J22: =IF(AND(E22<>"",F22<>""),F22/E22,"") -> 0.38521401 | K22: =IF(I22="","",IF(I22>=0.18,"✓ Cumple","✗ Por debajo")) -> ✓ Cumple | L22: =IF(J22="","",IF(J22>=0.075,"✓ Cumple","✗ Por debajo")) -> ✓ Cumple
A23: 2022 | B23: Agosto | C23: 2722 | E23: 542 | F23: 147 | G23: 17 | H23: 5 | I23: =IF(AND(C23<>"",E23<>""),E23/C23,"") -> 0.1991183 | J23: =IF(AND(E23<>"",F23<>""),F23/E23,"") -> 0.27121771 | K23: =IF(I23="","",IF(I23>=0.18,"✓ Cumple","✗ Por debajo")) -> ✓ Cumple | L23: =IF(J23="","",IF(J23>=0.075,"✓ Cumple","✗ Por debajo")) -> ✓ Cumple
A24: 2022 | B24: Setiembre | C24: 2726 | E24: 308 | F24: 36 | G24: 7 | H24: 4 | I24: =IF(AND(C24<>"",E24<>""),E24/C24,"") -> 0.11298606 | J24: =IF(AND(E24<>"",F24<>""),F24/E24,"") -> 0.11688312 | K24: =IF(I24="","",IF(I24>=0.18,"✓ Cumple","✗ Por debajo")) -> ✗ Por debajo | L24: =IF(J24="","",IF(J24>=0.075,"✓ Cumple","✗ Por debajo")) -> ✓ Cumple
A25: 2022 | B25: Octubre | C25: 2726 | E25: 446 | F25: 147 | G25: 12 | H25: 4 | I25: =IF(AND(C25<>"",E25<>""),E25/C25,"") -> 0.16360968 | J25: =IF(AND(E25<>"",F25<>""),F25/E25,"") -> 0.32959641 | K25: =IF(I25="","",IF(I25>=0.18,"✓ Cumple","✗ Por debajo")) -> ✗ Por debajo | L25: =IF(J25="","",IF(J25>=0.075,"✓ Cumple","✗ Por debajo")) -> ✓ Cumple
A26: 2022 | B26: Noviembre | C26: 2760 | E26: 961 | F26: 178 | G26: 6 | H26: 3 | I26: =IF(AND(C26<>"",E26<>""),E26/C26,"") -> 0.34818841 | J26: =IF(AND(E26<>"",F26<>""),F26/E26,"") -> 0.18522373 | K26: =IF(I26="","",IF(I26>=0.18,"✓ Cumple","✗ Por debajo")) -> ✓ Cumple | L26: =IF(J26="","",IF(J26>=0.075,"✓ Cumple","✗ Por debajo")) -> ✓ Cumple
A27: 2022 | B27: Diciembre | C27: 2760 | E27: 1041 | F27: 269 | G27: 35 | H27: 2 | I27: =IF(AND(C27<>"",E27<>""),E27/C27,"") -> 0.37717391 | J27: =IF(AND(E27<>"",F27<>""),F27/E27,"") -> 0.25840538 | K27: =IF(I27="","",IF(I27>=0.18,"✓ Cumple","✗ Por debajo")) -> ✓ Cumple | L27: =IF(J27="","",IF(J27>=0.075,"✓ Cumple","✗ Por debajo")) -> ✓ Cumple
A28: 2023 | B28: Enero | C28: 2865 | E28: 1596 | F28: 152 | G28: 43 | H28: 2 | I28: =IF(AND(C28<>"",E28<>""),E28/C28,"") -> 0.55706806 | J28: =IF(AND(E28<>"",F28<>""),F28/E28,"") -> 0.095238095 | K28: =IF(I28="","",IF(I28>=0.18,"✓ Cumple","✗ Por debajo")) -> ✓ Cumple | L28: =IF(J28="","",IF(J28>=0.075,"✓ Cumple","✗ Por debajo")) -> ✓ Cumple
A29: 2023 | B29: Febrero | C29: 2877 | D29: 3867 | E29: 795 | F29: 340 | G29: 19 | H29: 4 | I29: =IF(AND(C29<>"",E29<>""),E29/C29,"") -> 0.27632951 | J29: =IF(AND(E29<>"",F29<>""),F29/E29,"") -> 0.42767296 | K29: =IF(I29="","",IF(I29>=0.18,"✓ Cumple","✗ Por debajo")) -> ✓ Cumple | L29: =IF(J29="","",IF(J29>=0.075,"✓ Cumple","✗ Por debajo")) -> ✓ Cumple
A30: 2023 | B30: Marzo | C30: 2911 | E30: 436 | F30: 39 | G30: 24 | H30: 2 | I30: =IF(AND(C30<>"",E30<>""),E30/C30,"") -> 0.14977671 | J30: =IF(AND(E30<>"",F30<>""),F30/E30,"") -> 0.089449541 | K30: =IF(I30="","",IF(I30>=0.18,"✓ Cumple","✗ Por debajo")) -> ✗ Por debajo | L30: =IF(J30="","",IF(J30>=0.075,"✓ Cumple","✗ Por debajo")) -> ✓ Cumple
A31: 2023 | B31: Abril | C31: 2911 | D31: 1123 | E31: 136 | F31: 20 | G31: 2 | H31: 2 | I31: =IF(AND(C31<>"",E31<>""),E31/C31,"") -> 0.04671934 | J31: =IF(AND(E31<>"",F31<>""),F31/E31,"") -> 0.14705882 | K31: =IF(I31="","",IF(I31>=0.18,"✓ Cumple","✗ Por debajo")) -> ✗ Por debajo | L31: =IF(J31="","",IF(J31>=0.075,"✓ Cumple","✗ Por debajo")) -> ✓ Cumple
A32: 2023 | B32: Mayo | C32: 2939 | D32: 398 | E32: 203 | F32: 9 | G32: 5 | H32: 5 | I32: =IF(AND(C32<>"",E32<>""),E32/C32,"") -> 0.069071113 | J32: =IF(AND(E32<>"",F32<>""),F32/E32,"") -> 0.044334975 | K32: =IF(I32="","",IF(I32>=0.18,"✓ Cumple","✗ Por debajo")) -> ✗ Por debajo | L32: =IF(J32="","",IF(J32>=0.075,"✓ Cumple","✗ Por debajo")) -> ✗ Por debajo
A33: 2023 | B33: Junio | C33: 2957 | D33: 688 | E33: 144 | F33: 9 | G33: 4 | H33: 4 | I33: =IF(AND(C33<>"",E33<>""),E33/C33,"") -> 0.048698005 | J33: =IF(AND(E33<>"",F33<>""),F33/E33,"") -> 0.0625 | K33: =IF(I33="","",IF(I33>=0.18,"✓ Cumple","✗ Por debajo")) -> ✗ Por debajo | L33: =IF(J33="","",IF(J33>=0.075,"✓ Cumple","✗ Por debajo")) -> ✗ Por debajo
A34: 2023 | B34: Julio | C34: 2957 | D34: 850 | E34: 213 | F34: 17 | G34: 3 | H34: 3 | I34: =IF(AND(C34<>"",E34<>""),E34/C34,"") -> 0.072032465 | J34: =IF(AND(E34<>"",F34<>""),F34/E34,"") -> 0.079812207 | K34: =IF(I34="","",IF(I34>=0.18,"✓ Cumple","✗ Por debajo")) -> ✗ Por debajo | L34: =IF(J34="","",IF(J34>=0.075,"✓ Cumple","✗ Por debajo")) -> ✓ Cumple
A35: 2023 | B35: Agosto | C35: 2796 | D35: 1113 | E35: 285 | F35: 13 | G35: 3 | H35: 3 | I35: =IF(AND(C35<>"",E35<>""),E35/C35,"") -> 0.10193133 | J35: =IF(AND(E35<>"",F35<>""),F35/E35,"") -> 0.045614035 | K35: =IF(I35="","",IF(I35>=0.18,"✓ Cumple","✗ Por debajo")) -> ✗ Por debajo | L35: =IF(J35="","",IF(J35>=0.075,"✓ Cumple","✗ Por debajo")) -> ✗ Por debajo
A36: 2023 | B36: Setiembre | C36: 2796 | D36: 1085 | E36: 23 | F36: 4 | G36: 1 | H36: 1 | I36: =IF(AND(C36<>"",E36<>""),E36/C36,"") -> 0.0082260372 | J36: =IF(AND(E36<>"",F36<>""),F36/E36,"") -> 0.17391304 | K36: =IF(I36="","",IF(I36>=0.18,"✓ Cumple","✗ Por debajo")) -> ✗ Por debajo | L36: =IF(J36="","",IF(J36>=0.075,"✓ Cumple","✗ Por debajo")) -> ✓ Cumple
A37: 2023 | B37: Octubre | C37: 2801 | D37: 1641 | E37: 64 | F37: 5 | G37: 1 | H37: 1 | I37: =IF(AND(C37<>"",E37<>""),E37/C37,"") -> 0.022848983 | J37: =IF(AND(E37<>"",F37<>""),F37/E37,"") -> 0.078125 | K37: =IF(I37="","",IF(I37>=0.18,"✓ Cumple","✗ Por debajo")) -> ✗ Por debajo | L37: =IF(J37="","",IF(J37>=0.075,"✓ Cumple","✗ Por debajo")) -> ✓ Cumple
A38: 2023 | B38: Noviembre | C38: 2801 | D38: 433 | E38: 0 | F38: 0 | G38: 0 | H38: 0 | I38: =IF(AND(C38<>"",E38<>""),E38/C38,"") -> 0 | K38: =IF(I38="","",IF(I38>=0.18,"✓ Cumple","✗ Por debajo")) -> ✗ Por debajo | L38: =IF(J38="","",IF(J38>=0.075,"✓ Cumple","✗ Por debajo"))
A39: 2023 | B39: Diciembre | C39: 3040 | D39: 1012 | E39: 1012 | F39: 96 | G39: 3 | H39: 2 | I39: =IF(AND(C39<>"",E39<>""),E39/C39,"") -> 0.33289474 | J39: =IF(AND(E39<>"",F39<>""),F39/E39,"") -> 0.09486166 | K39: =IF(I39="","",IF(I39>=0.18,"✓ Cumple","✗ Por debajo")) -> ✓ Cumple | L39: =IF(J39="","",IF(J39>=0.075,"✓ Cumple","✗ Por debajo")) -> ✓ Cumple
A40: 2024 | B40: Enero | C40: 3052 | E40: 770 | F40: 15 | G40: 13 | H40: 1 | I40: =IF(AND(C40<>"",E40<>""),E40/C40,"") -> 0.25229358 | J40: =IF(AND(E40<>"",F40<>""),F40/E40,"") -> 0.019480519 | K40: =IF(I40="","",IF(I40>=0.18,"✓ Cumple","✗ Por debajo")) -> ✓ Cumple | L40: =IF(J40="","",IF(J40>=0.075,"✓ Cumple","✗ Por debajo")) -> ✗ Por debajo
A41: 2024 | B41: Febrero | C41: 3066 | D41: 2759 | E41: 1294 | F41: 147 | G41: 14 | H41: 2 | I41: =IF(AND(C41<>"",E41<>""),E41/C41,"") -> 0.42204827 | J41: =IF(AND(E41<>"",F41<>""),F41/E41,"") -> 0.11360124 | K41: =IF(I41="","",IF(I41>=0.18,"✓ Cumple","✗ Por debajo")) -> ✓ Cumple | L41: =IF(J41="","",IF(J41>=0.075,"✓ Cumple","✗ Por debajo")) -> ✓ Cumple
A42: 2024 | B42: Marzo | C42: 3085 | D42: 2759 | E42: 1119 | F42: 72 | G42: 24 | H42: 1 | I42: =IF(AND(C42<>"",E42<>""),E42/C42,"") -> 0.36272285 | J42: =IF(AND(E42<>"",F42<>""),F42/E42,"") -> 0.064343164 | K42: =IF(I42="","",IF(I42>=0.18,"✓ Cumple","✗ Por debajo")) -> ✓ Cumple | L42: =IF(J42="","",IF(J42>=0.075,"✓ Cumple","✗ Por debajo")) -> ✗ Por debajo
A43: 2024 | B43: Abril | C43: 3090 | D43: 1123 | E43: 1031 | F43: 52 | G43: 10 | H43: 1 | I43: =IF(AND(C43<>"",E43<>""),E43/C43,"") -> 0.33365696 | J43: =IF(AND(E43<>"",F43<>""),F43/E43,"") -> 0.050436469 | K43: =IF(I43="","",IF(I43>=0.18,"✓ Cumple","✗ Por debajo")) -> ✓ Cumple | L43: =IF(J43="","",IF(J43>=0.075,"✓ Cumple","✗ Por debajo")) -> ✗ Por debajo
A44: 2024 | B44: Mayo | C44: 3097 | D44: 2237 | E44: 496 | F44: 92 | G44: 7 | H44: 3 | I44: =IF(AND(C44<>"",E44<>""),E44/C44,"") -> 0.16015499 | J44: =IF(AND(E44<>"",F44<>""),F44/E44,"") -> 0.18548387 | K44: =IF(I44="","",IF(I44>=0.18,"✓ Cumple","✗ Por debajo")) -> ✗ Por debajo | L44: =IF(J44="","",IF(J44>=0.075,"✓ Cumple","✗ Por debajo")) -> ✓ Cumple
A45: 2024 | B45: Junio | C45: 3108 | D45: 401 | E45: 34 | F45: 11 | G45: 1 | H45: 1 | I45: =IF(AND(C45<>"",E45<>""),E45/C45,"") -> 0.010939511 | J45: =IF(AND(E45<>"",F45<>""),F45/E45,"") -> 0.32352941 | K45: =IF(I45="","",IF(I45>=0.18,"✓ Cumple","✗ Por debajo")) -> ✗ Por debajo | L45: =IF(J45="","",IF(J45>=0.075,"✓ Cumple","✗ Por debajo")) -> ✓ Cumple
A46: 2024 | B46: Julio | C46: 3108 | D46: 376 | E46: 76 | F46: 13 | G46: 3 | H46: 3 | I46: =IF(AND(C46<>"",E46<>""),E46/C46,"") -> 0.024453024 | J46: =IF(AND(E46<>"",F46<>""),F46/E46,"") -> 0.17105263 | K46: =IF(I46="","",IF(I46>=0.18,"✓ Cumple","✗ Por debajo")) -> ✗ Por debajo | L46: =IF(J46="","",IF(J46>=0.075,"✓ Cumple","✗ Por debajo")) -> ✓ Cumple
A47: 2024 | B47: Agosto | C47: 3114 | D47: 312 | E47: 249 | F47: 60 | G47: 6 | H47: 1 | I47: =IF(AND(C47<>"",E47<>""),E47/C47,"") -> 0.079961464 | J47: =IF(AND(E47<>"",F47<>""),F47/E47,"") -> 0.24096386 | K47: =IF(I47="","",IF(I47>=0.18,"✓ Cumple","✗ Por debajo")) -> ✗ Por debajo | L47: =IF(J47="","",IF(J47>=0.075,"✓ Cumple","✗ Por debajo")) -> ✓ Cumple
A48: 2024 | B48: Setiembre | C48: 3120 | D48: 979 | E48: 939 | F48: 24 | G48: 17 | H48: 1 | I48: =IF(AND(C48<>"",E48<>""),E48/C48,"") -> 0.30096154 | J48: =IF(AND(E48<>"",F48<>""),F48/E48,"") -> 0.025559105 | K48: =IF(I48="","",IF(I48>=0.18,"✓ Cumple","✗ Por debajo")) -> ✓ Cumple | L48: =IF(J48="","",IF(J48>=0.075,"✓ Cumple","✗ Por debajo")) -> ✗ Por debajo
A49: 2024 | B49: Octubre | C49: 3120 | D49: 1846 | E49: 502 | F49: 17 | G49: 6 | H49: 1 | I49: =IF(AND(C49<>"",E49<>""),E49/C49,"") -> 0.16089744 | J49: =IF(AND(E49<>"",F49<>""),F49/E49,"") -> 0.033864542 | K49: =IF(I49="","",IF(I49>=0.18,"✓ Cumple","✗ Por debajo")) -> ✗ Por debajo | L49: =IF(J49="","",IF(J49>=0.075,"✓ Cumple","✗ Por debajo")) -> ✗ Por debajo
A50: 2024 | B50: Noviembre | C50: 3120 | D50: 1088 | E50: 134 | F50: 5 | G50: 8 | H50: 0 | I50: =IF(AND(C50<>"",E50<>""),E50/C50,"") -> 0.042948718 | J50: =IF(AND(E50<>"",F50<>""),F50/E50,"") -> 0.037313433 | K50: =IF(I50="","",IF(I50>=0.18,"✓ Cumple","✗ Por debajo")) -> ✗ Por debajo | L50: =IF(J50="","",IF(J50>=0.075,"✓ Cumple","✗ Por debajo")) -> ✗ Por debajo
A51: 2024 | B51: Diciembre | C51: 3123 | D51: 3326 | E51: 577 | F51: 57 | G51: 6 | H51: 1 | I51: =IF(AND(C51<>"",E51<>""),E51/C51,"") -> 0.18475825 | J51: =IF(AND(E51<>"",F51<>""),F51/E51,"") -> 0.098786828 | K51: =IF(I51="","",IF(I51>=0.18,"✓ Cumple","✗ Por debajo")) -> ✓ Cumple | L51: =IF(J51="","",IF(J51>=0.075,"✓ Cumple","✗ Por debajo")) -> ✓ Cumple
A52: 2025 | B52: Enero | C52: 3124 | D52: 1721 | E52: 299 | F52: 14 | G52: 6 | H52: 0 | I52: =IF(AND(C52<>"",E52<>""),E52/C52,"") -> 0.095710627 | J52: =IF(AND(E52<>"",F52<>""),F52/E52,"") -> 0.046822742 | K52: =IF(I52="","",IF(I52>=0.18,"✓ Cumple","✗ Por debajo")) -> ✗ Por debajo | L52: =IF(J52="","",IF(J52>=0.075,"✓ Cumple","✗ Por debajo")) -> ✗ Por debajo
... A68: 2026 | B68: Mayo | C68: 3184 | D68: 5105 | E68: 1567 | F68: 108 | G68: 22 | H68: 2 | I68: =IF(AND(C68<>"",E68<>""),E68/C68,"") -> 0.49214824 | J68: =IF(AND(E68<>"",F68<>""),F68/E68,"") -> 0.068921506 | K68: =IF(I68="","",IF(I68>=0.18,"✓ Cumple","✗ Por debajo")) -> ✓ Cumple | L68: =IF(J68="","",IF(J68>=0.075,"✓ Cumple","✗ Por debajo")) -> ✗ Por debajo
A69: 2026 | B69: Junio | I69: =IF(AND(C69<>"",E69<>""),E69/C69,"") | J69: =IF(AND(E69<>"",F69<>""),F69/E69,"") | K69: =IF(I69="","",IF(I69>=0.18,"✓ Cumple","✗ Por debajo")) | L69: =IF(J69="","",IF(J69>=0.075,"✓ Cumple","✗ Por debajo"))
A70: 2026 | B70: Julio | I70: =IF(AND(C70<>"",E70<>""),E70/C70,"") | J70: =IF(AND(E70<>"",F70<>""),F70/E70,"") | K70: =IF(I70="","",IF(I70>=0.18,"✓ Cumple","✗ Por debajo")) | L70: =IF(J70="","",IF(J70>=0.075,"✓ Cumple","✗ Por debajo"))
A71: 2026 | B71: Agosto | I71: =IF(AND(C71<>"",E71<>""),E71/C71,"") | J71: =IF(AND(E71<>"",F71<>""),F71/E71,"") | K71: =IF(I71="","",IF(I71>=0.18,"✓ Cumple","✗ Por debajo")) | L71: =IF(J71="","",IF(J71>=0.075,"✓ Cumple","✗ Por debajo"))
A72: 2026 | B72: Setiembre | I72: =IF(AND(C72<>"",E72<>""),E72/C72,"") | J72: =IF(AND(E72<>"",F72<>""),F72/E72,"") | K72: =IF(I72="","",IF(I72>=0.18,"✓ Cumple","✗ Por debajo")) | L72: =IF(J72="","",IF(J72>=0.075,"✓ Cumple","✗ Por debajo"))
A73: 2026 | B73: Octubre | I73: =IF(AND(C73<>"",E73<>""),E73/C73,"") | J73: =IF(AND(E73<>"",F73<>""),F73/E73,"") | K73: =IF(I73="","",IF(I73>=0.18,"✓ Cumple","✗ Por debajo")) | L73: =IF(J73="","",IF(J73>=0.075,"✓ Cumple","✗ Por debajo"))
A74: 2026 | B74: Noviembre | I74: =IF(AND(C74<>"",E74<>""),E74/C74,"") | J74: =IF(AND(E74<>"",F74<>""),F74/E74,"") | K74: =IF(I74="","",IF(I74>=0.18,"✓ Cumple","✗ Por debajo")) | L74: =IF(J74="","",IF(J74>=0.075,"✓ Cumple","✗ Por debajo"))
A75: 2026 | B75: Diciembre | I75: =IF(AND(C75<>"",E75<>""),E75/C75,"") | J75: =IF(AND(E75<>"",F75<>""),F75/E75,"") | K75: =IF(I75="","",IF(I75>=0.18,"✓ Cumple","✗ Por debajo")) | L75: =IF(J75="","",IF(J75>=0.075,"✓ Cumple","✗ Por debajo"))

Sheet 💼 LinkedIn_KPIs
A1: PIL Perú — KPIs LinkedIn
A2: Benchmark: Alcance ≥ 18% de seguidores | Interacción ≥ 7.5% (Impresiones/Interacciones) — Azul = ingreso manual | Verde = fórmula
A3: Año | B3: Mes | C3: Seguidores Totales | D3: Impresiones | E3: Alcance | F3: Interacciones | G3: Nuevos Seguidores | H3: Posts Publicados | I3: % Alcance (Alc/Seg) | J3: % Interacción (Int/Imp) | K3: Estado Alcance | L3: Estado Interacción
A4: 2022 | B4: Enero | C4: 3115 | D4: 6054 | E4: 695 | F4: 339 | G4: 27 | H4: 5 | I4: =IF(AND(C4<>"",E4<>""),E4/C4,"") -> 0.22311396 | J4: =IF(AND(D4<>"",F4<>""),F4/D4,"") -> 0.055996036 | K4: =IF(I4="","",IF(I4>=0.18,"✓ Cumple","✗ Por debajo")) -> ✓ Cumple | L4: =IF(J4="","",IF(J4>=0.075,"✓ Cumple","✗ Por debajo")) -> ✗ Por debajo
A5: 2022 | B5: Febrero | C5: 3152 | D5: 6240 | E5: 1923 | F5: 601 | G5: 35 | H5: 3 | I5: =IF(AND(C5<>"",E5<>""),E5/C5,"") -> 0.61008883 | J5: =IF(AND(D5<>"",F5<>""),F5/D5,"") -> 0.096314103 | K5: =IF(I5="","",IF(I5>=0.18,"✓ Cumple","✗ Por debajo")) -> ✓ Cumple | L5: =IF(J5="","",IF(J5>=0.075,"✓ Cumple","✗ Por debajo")) -> ✓ Cumple
A6: 2022 | B6: Marzo | C6: 3194 | D6: 5635 | E6: 3330 | F6: 488 | G6: 42 | H6: 2 | I6: =IF(AND(C6<>"",E6<>""),E6/C6,"") -> 1.0425798 | J6: =IF(AND(D6<>"",F6<>""),F6/D6,"") -> 0.086601597 | K6: =IF(I6="","",IF(I6>=0.18,"✓ Cumple","✗ Por debajo")) -> ✓ Cumple | L6: =IF(J6="","",IF(J6>=0.075,"✓ Cumple","✗ Por debajo")) -> ✓ Cumple
A7: 2022 | B7: Abril | C7: 3232 | D7: 2814 | E7: 559 | F7: 349 | G7: 29 | H7: 3 | I7: =IF(AND(C7<>"",E7<>""),E7/C7,"") -> 0.17295792 | J7: =IF(AND(D7<>"",F7<>""),F7/D7,"") -> 0.12402274 | K7: =IF(I7="","",IF(I7>=0.18,"✓ Cumple","✗ Por debajo")) -> ✗ Por debajo | L7: =IF(J7="","",IF(J7>=0.075,"✓ Cumple","✗ Por debajo")) -> ✓ Cumple
A8: 2022 | B8: Mayo | C8: 3273 | D8: 4634 | E8: 718 | F8: 341 | G8: 41 | H8: 4 | I8: =IF(AND(C8<>"",E8<>""),E8/C8,"") -> 0.21937061 | J8: =IF(AND(D8<>"",F8<>""),F8/D8,"") -> 0.073586534 | K8: =IF(I8="","",IF(I8>=0.18,"✓ Cumple","✗ Por debajo")) -> ✓ Cumple | L8: =IF(J8="","",IF(J8>=0.075,"✓ Cumple","✗ Por debajo")) -> ✗ Por debajo
A9: 2022 | B9: Junio | C9: 3304 | D9: 3752 | E9: 429 | F9: 152 | G9: 32 | H9: 5 | I9: =IF(AND(C9<>"",E9<>""),E9/C9,"") -> 0.12984262 | J9: =IF(AND(D9<>"",F9<>""),F9/D9,"") -> 0.040511727 | K9: =IF(I9="","",IF(I9>=0.18,"✓ Cumple","✗ Por debajo")) -> ✗ Por debajo | L9: =IF(J9="","",IF(J9>=0.075,"✓ Cumple","✗ Por debajo")) -> ✗ Por debajo
A10: 2022 | B10: Julio | C10: 3314 | D10: 4884 | E10: 975 | F10: 198 | G10: 26 | H10: 3 | I10: =IF(AND(C10<>"",E10<>""),E10/C10,"") -> 0.2942064 | J10: =IF(AND(D10<>"",F10<>""),F10/D10,"") -> 0.040540541 | K10: =IF(I10="","",IF(I10>=0.18,"✓ Cumple","✗ Por debajo")) -> ✓ Cumple | L10: =IF(J10="","",IF(J10>=0.075,"✓ Cumple","✗ Por debajo")) -> ✗ Por debajo
A11: 2022 | B11: Agosto | C11: 3348 | D11: 5385 | E11: 665 | F11: 367 | G11: 34 | H11: 5 | I11: =IF(AND(C11<>"",E11<>""),E11/C11,"") -> 0.19862605 | J11: =IF(AND(D11<>"",F11<>""),F11/D11,"") -> 0.068152275 | K11: =IF(I11="","",IF(I11>=0.18,"✓ Cumple","✗ Por debajo")) -> ✓ Cumple | L11: =IF(J11="","",IF(J11>=0.075,"✓ Cumple","✗ Por debajo")) -> ✗ Por debajo
A12: 2022 | B12: Setiembre | C12: 3470 | D12: 5491 | E12: 743 | F12: 347 | G12: 135 | H12: 4 | I12: =IF(AND(C12<>"",E12<>""),E12/C12,"") -> 0.21412104 | J12: =IF(AND(D12<>"",F12<>""),F12/D12,"") -> 0.063194318 | K12: =IF(I12="","",IF(I12>=0.18,"✓ Cumple","✗ Por debajo")) -> ✓ Cumple | L12: =IF(J12="","",IF(J12>=0.075,"✓ Cumple","✗ Por debajo")) -> ✗ Por debajo
A13: 2022 | B13: Octubre | C13: 3470 | D13: 6408 | E13: 1602 | F13: 256 | G13: 31 | H13: 4 | I13: =IF(AND(C13<>"",E13<>""),E13/C13,"") -> 0.46167147 | J13: =IF(AND(D13<>"",F13<>""),F13/D13,"") -> 0.039950062 | K13: =IF(I13="","",IF(I13>=0.18,"✓ Cumple","✗ Por debajo")) -> ✓ Cumple | L13: =IF(J13="","",IF(J13>=0.075,"✓ Cumple","✗ Por debajo")) -> ✗ Por debajo
A14: 2022 | B14: Noviembre | C14: 3690 | D14: 6406 | E14: 1188 | F14: 730 | G14: 112 | H14: 3 | I14: =IF(AND(C14<>"",E14<>""),E14/C14,"") -> 0.32195122 | J14: =IF(AND(D14<>"",F14<>""),F14/D14,"") -> 0.11395567 | K14: =IF(I14="","",IF(I14>=0.18,"✓ Cumple","✗ Por debajo")) -> ✓ Cumple | L14: =IF(J14="","",IF(J14>=0.075,"✓ Cumple","✗ Por debajo")) -> ✓ Cumple
A15: 2022 | B15: Diciembre | C15: 3690 | D15: 6406 | E15: 1188 | F15: 730 | G15: 112 | H15: 2 | I15: =IF(AND(C15<>"",E15<>""),E15/C15,"") -> 0.32195122 | J15: =IF(AND(D15<>"",F15<>""),F15/D15,"") -> 0.11395567 | K15: =IF(I15="","",IF(I15>=0.18,"✓ Cumple","✗ Por debajo")) -> ✓ Cumple | L15: =IF(J15="","",IF(J15>=0.075,"✓ Cumple","✗ Por debajo")) -> ✓ Cumple
... A56: 2026 | B56: Mayo | C56: 6280 | D56: 7.219 | E56: 3223 | F56: 819 | G56: 129 | H56: 2 | I56: =IF(AND(C56<>"",E56<>""),E56/C56,"") -> 0.51321656 | J56: =IF(AND(D56<>"",F56<>""),F56/D56,"") -> 113.45062 | K56: =IF(I56="","",IF(I56>=0.18,"✓ Cumple","✗ Por debajo")) -> ✓ Cumple | L56: =IF(J56="","",IF(J56>=0.075,"✓ Cumple","✗ Por debajo")) -> ✓ Cumple
A57: 2026 | B57: Junio | I57: =IF(AND(C57<>"",E57<>""),E57/C57,"") | J57: =IF(AND(D57<>"",F57<>""),F57/D57,"") | K57: =IF(I57="","",IF(I57>=0.18,"✓ Cumple","✗ Por debajo")) | L57: =IF(J57="","",IF(J57>=0.075,"✓ Cumple","✗ Por debajo"))
A58: 2026 | B58: Julio | I58: =IF(AND(C58<>"",E58<>""),E58/C58,"") | J58: =IF(AND(D58<>"",F58<>""),F58/D58,"") | K58: =IF(I58="","",IF(I58>=0.18,"✓ Cumple","✗ Por debajo")) | L58: =IF(J58="","",IF(J58>=0.075,"✓ Cumple","✗ Por debajo"))
A59: 2026 | B59: Agosto | I59: =IF(AND(C59<>"",E59<>""),E59/C59,"") | J59: =IF(AND(D59<>"",F59<>""),F59/D59,"") | K59: =IF(I59="","",IF(I59>=0.18,"✓ Cumple","✗ Por debajo")) | L59: =IF(J59="","",IF(J59>=0.075,"✓ Cumple","✗ Por debajo"))
A60: 2026 | B60: Setiembre | I60: =IF(AND(C60<>"",E60<>""),E60/C60,"") | J60: =IF(AND(D60<>"",F60<>""),F60/D60,"") | K60: =IF(I60="","",IF(I60>=0.18,"✓ Cumple","✗ Por debajo")) | L60: =IF(J60="","",IF(J60>=0.075,"✓ Cumple","✗ Por debajo"))
A61: 2026 | B61: Octubre | I61: =IF(AND(C61<>"",E61<>""),E61/C61,"") | J61: =IF(AND(D61<>"",F61<>""),F61/D61,"") | K61: =IF(I61="","",IF(I61>=0.18,"✓ Cumple","✗ Por debajo")) | L61: =IF(J61="","",IF(J61>=0.075,"✓ Cumple","✗ Por debajo"))
A62: 2026 | B62: Noviembre | I62: =IF(AND(C62<>"",E62<>""),E62/C62,"") | J62: =IF(AND(D62<>"",F62<>""),F62/D62,"") | K62: =IF(I62="","",IF(I62>=0.18,"✓ Cumple","✗ Por debajo")) | L62: =IF(J62="","",IF(J62>=0.075,"✓ Cumple","✗ Por debajo"))
A63: 2026 | B63: Diciembre | I63: =IF(AND(C63<>"",E63<>""),E63/C63,"") | J63: =IF(AND(D63<>"",F63<>""),F63/D63,"") | K63: =IF(I63="","",IF(I63>=0.18,"✓ Cumple","✗ Por debajo")) | L63: =IF(J63="","",IF(J63>=0.075,"✓ Cumple","✗ Por debajo"))

Sheet 🌐 Web_Visitas
A1: PIL Perú — Tráfico Web · pil.com.pe
A2: Mes | B2: 2021 | C2: 2022 | D2: 2023 | E2: 2024 | F2: 2025 | G2: 2026 | H2: Var. 2026 vs 2025 | I2: Mejor Año
A3: Enero | B3: 860 | C3: 4429 | D3: 6415 | E3: 5056 | F3: 4965 | G3: 4818 | H3: =IF(OR(G3="",F3="",F3=0),"",(G3-F3)/F3) -> -0.029607251 | I3: =IF(COUNTA(B3:G3)=0,"",MAX(B3:G3)) -> 6415
A4: Febrero | B4: 814 | C4: 3733 | D4: 5769 | E4: 4869 | F4: 4639 | G4: 4068 | H4: =IF(OR(G4="",F4="",F4=0),"",(G4-F4)/F4) -> -0.12308687 | I4: =IF(COUNTA(B4:G4)=0,"",MAX(B4:G4)) -> 5769
A5: Marzo | B5: 1417 | C5: 4273 | D5: 5629 | E5: 4490 | F5: 5542 | G5: 4331 | H5: =IF(OR(G5="",F5="",F5=0),"",(G5-F5)/F5) -> -0.21851317 | I5: =IF(COUNTA(B5:G5)=0,"",MAX(B5:G5)) -> 5629
A6: Abril | B6: 1616 | C6: 5158 | D6: 4465 | E6: 4506 | F6: 4616 | G6: 3641 | H6: =IF(OR(G6="",F6="",F6=0),"",(G6-F6)/F6) -> -0.21122184 | I6: =IF(COUNTA(B6:G6)=0,"",MAX(B6:G6)) -> 5158
A7: Mayo | B7: 2244 | C7: 9636 | D7: 3930 | E7: 4400 | F7: 4291 | G7: 4837 | H7: =IF(OR(G7="",F7="",F7=0),"",(G7-F7)/F7) -> 0.12724307 | I7: =IF(COUNTA(B7:G7)=0,"",MAX(B7:G7)) -> 9636
A8: Junio | B8: 1828 | C8: 4058 | D8: 3990 | E8: 4262 | F8: 5139 | H8: =IF(OR(G8="",F8="",F8=0),"",(G8-F8)/F8) | I8: =IF(COUNTA(B8:G8)=0,"",MAX(B8:G8)) -> 5139
A9: Julio | B9: 1456 | C9: 4636 | D9: 3725 | E9: 4822 | F9: 5589 | H9: =IF(OR(G9="",F9="",F9=0),"",(G9-F9)/F9) | I9: =IF(COUNTA(B9:G9)=0,"",MAX(B9:G9)) -> 5589
A10: Agosto | B10: 1472 | C10: 4353 | D10: 4038 | E10: 5021 | F10: 5613 | H10: =IF(OR(G10="",F10="",F10=0),"",(G10-F10)/F10) | I10: =IF(COUNTA(B10:G10)=0,"",MAX(B10:G10)) -> 5613
A11: Setiembre | B11: 1804 | C11: 5247 | D11: 5221 | E11: 5125 | F11: 5650 | H11: =IF(OR(G11="",F11="",F11=0),"",(G11-F11)/F11) | I11: =IF(COUNTA(B11:G11)=0,"",MAX(B11:G11)) -> 5650
A12: Octubre | B12: 2440 | C12: 5834 | D12: 4974 | E12: 5770 | F12: 5604 | H12: =IF(OR(G12="",F12="",F12=0),"",(G12-F12)/F12) | I12: =IF(COUNTA(B12:G12)=0,"",MAX(B12:G12)) -> 5834
A13: Noviembre | B13: 1339 | C13: 6294 | D13: 4401 | E13: 5264 | F13: 5278 | H13: =IF(OR(G13="",F13="",F13=0),"",(G13-F13)/F13) | I13: =IF(COUNTA(B13:G13)=0,"",MAX(B13:G13)) -> 6294
A14: Diciembre | B14: 5253 | C14: 6372 | D14: 4626 | E14: 5081 | F14: 5142 | H14: =IF(OR(G14="",F14="",F14=0),"",(G14-F14)/F14) | I14: =IF(COUNTA(B14:G14)=0,"",MAX(B14:G14)) -> 6372
A15: TOTAL | B15: =SUM(B3:B14) -> 22543 | C15: =SUM(C3:C14) -> 64023 | D15: =SUM(D3:D14) -> 57183 | E15: =SUM(E3:E14) -> 58666 | F15: =SUM(F3:F14) -> 62068 | G15: =SUM(G3:G14) -> 21695

Sheet 🔍 GSC_SearchConsole
A1: PIL Perú — Google Search Console · pil.com.pe
A2: Año | B2: Mes | C2: Clics Orgánicos | D2: Impresiones GSC | E2: CTR (%) | F2: Posición Media | G2: Nota / Observación
A3: 2026 | B3: Enero | C3: 334 | D3: 5603 | E3: 6
A4: 2026 | B4: Febrero | C4: 266 | D4: 5483 | E4: 4.9
A5: 2026 | B5: Marzo | C5: 385 | D5: 7098 | E5: 5.1
A6: 2026 | B6: Abril | C6: 393 | D6: 7755 | E6: 5.1 | F6: 1.47 | G6: Posición 1.47 para 'pil peru'
A7: 2026 | B7: Mayo | C7: 449 | D7: 5961 | E7: =C7/D7 -> 0.075322932
A8: 2026 | B8: Junio
A9: 2026 | B9: Julio
A10: 2026 | B10: Agosto
A11: 2026 | B11: Setiembre
A12: 2026 | B12: Octubre
A13: 2026 | B13: Noviembre
A14: 2026 | B14: Diciembre

Sheet 📊 GA4_Analytics
A1: PIL Perú — Google Analytics 4 · pil.com.pe
A2: Año | B2: Mes | C2: Usuarios Totales | D2: Usuarios Nuevos | E2: Usuarios Recurrentes | F2: % Nuevos | G2: T. Interacción (seg) | H2: Sesiones / Usuario | I2: Eventos Totales | J2: Organic Search % | K2: Usuarios Organic Search
A3: 2026 | B3: Enero | C3: 722 | D3: 677 | F3: =IF(AND(C3<>"",D3<>""),D3/C3,"") -> 0.93767313 | J3: =IF(AND(K3<>"",C3<>""),K3/C3*100,"")
A4: 2026 | B4: Febrero | C4: 559 | D4: 519 | F4: =IF(AND(C4<>"",D4<>""),D4/C4,"") -> 0.92844365 | J4: =IF(AND(K4<>"",C4<>""),K4/C4*100,"")
A5: 2026 | B5: Marzo | C5: 604 | D5: 571 | F5: =IF(AND(C5<>"",D5<>""),D5/C5,"") -> 0.94536424 | J5: =IF(AND(K5<>"",C5<>""),K5/C5*100,"")
A6: 2026 | B6: Abril | C6: 547 | D6: 521 | E6: 109 | F6: =IF(AND(C6<>"",D6<>""),D6/C6,"") -> 0.95246801 | G6: 40 | H6: 0.71 | I6: 4210 | J6: =IF(AND(K6<>"",C6<>""),K6/C6*100,"") -> 69.104205 | K6: 378
A7: 2026 | B7: Mayo | C7: 683 | D7: 641 | F7: =IF(AND(C7<>"",D7<>""),D7/C7,"") -> 0.93850659 | J7: =IF(AND(K7<>"",C7<>""),K7/C7*100,"")
A8: 2026 | B8: Junio | F8: =IF(AND(C8<>"",D8<>""),D8/C8,"") | J8: =IF(AND(K8<>"",C8<>""),K8/C8*100,"")
A9: 2026 | B9: Julio | F9: =IF(AND(C9<>"",D9<>""),D9/C9,"") | J9: =IF(AND(K9<>"",C9<>""),K9/C9*100,"")
A10: 2026 | B10: Agosto | F10: =IF(AND(C10<>"",D10<>""),D10/C10,"") | J10: =IF(AND(K10<>"",C10<>""),K10/C10*100,"")
A11: 2026 | B11: Setiembre | F11: =IF(AND(C11<>"",D11<>""),D11/C11,"") | J11: =IF(AND(K11<>"",C11<>""),K11/C11*100,"")
A12: 2026 | B12: Octubre | F12: =IF(AND(C12<>"",D12<>""),D12/C12,"") | J12: =IF(AND(K12<>"",C12<>""),K12/C12*100,"")
A13: 2026 | B13: Noviembre | F13: =IF(AND(C13<>"",D13<>""),D13/C13,"") | J13: =IF(AND(K13<>"",C13<>""),K13/C13*100,"")
A14: 2026 | B14: Diciembre | F14: =IF(AND(C14<>"",D14<>""),D14/C14,"") | J14: =IF(AND(K14<>"",C14<>""),K14/C14*100,"")
A16: CONVERSIONES GA4 — Ingreso manual · Fuente: GA4 → Informes → Eventos
A17: Año | B17: Mes | C17: WhatsApp Click (eventos) | D17: WhatsApp Click (usuarios) | E17: Email Click (eventos) | F17: Email Click (usuarios) | G17: Generate Lead (eventos) | H17: Generate Lead (usuarios) | I17: File Download (eventos) | J17: File Download (usuarios) | K17: Tasa Lead Real (auto)
A18: 2026 | B18: Enero | K18: =IF(AND(C3<>"",OR(D18<>"",F18<>"")), (IF(D18<>"",D18,0)+IF(F18<>"",F18,0))/C3*100,"")
A19: 2026 | B19: Febrero | K19: =IF(AND(C4<>"",OR(D19<>"",F19<>"")), (IF(D19<>"",D19,0)+IF(F19<>"",F19,0))/C4*100,"")
A20: 2026 | B20: Marzo | K20: =IF(AND(C5<>"",OR(D20<>"",F20<>"")), (IF(D20<>"",D20,0)+IF(F20<>"",F20,0))/C5*100,"")
A21: 2026 | B21: Abril | K21: =IF(AND(C6<>"",OR(D21<>"",F21<>"")), (IF(D21<>"",D21,0)+IF(F21<>"",F21,0))/C6*100,"")
A22: 2026 | B22: Mayo | K22: =IF(AND(C7<>"",OR(D22<>"",F22<>"")), (IF(D22<>"",D22,0)+IF(F22<>"",F22,0))/C7*100,"")
A23: 2026 | B23: Junio | K23: =IF(AND(C8<>"",OR(D23<>"",F23<>"")), (IF(D23<>"",D23,0)+IF(F23<>"",F23,0))/C8*100,"")
A24: 2026 | B24: Julio | K24: =IF(AND(C9<>"",OR(D24<>"",F24<>"")), (IF(D24<>"",D24,0)+IF(F24<>"",F24,0))/C9*100,"")
A25: 2026 | B25: Agosto | K25: =IF(AND(C10<>"",OR(D25<>"",F25<>"")), (IF(D25<>"",D25,0)+IF(F25<>"",F25,0))/C10*100,"")
A26: 2026 | B26: Setiembre | K26: =IF(AND(C11<>"",OR(D26<>"",F26<>"")), (IF(D26<>"",D26,0)+IF(F26<>"",F26,0))/C11*100,"")
A27: 2026 | B27: Octubre | K27: =IF(AND(C12<>"",OR(D27<>"",F27<>"")), (IF(D27<>"",D27,0)+IF(F27<>"",F27,0))/C12*100,"")
A28: 2026 | B28: Noviembre | K28: =IF(AND(C13<>"",OR(D28<>"",F28<>"")), (IF(D28<>"",D28,0)+IF(F28<>"",F28,0))/C13*100,"")
A29: 2026 | B29: Diciembre | K29: =IF(AND(C14<>"",OR(D29<>"",F29<>"")), (IF(D29<>"",D29,0)+IF(F29<>"",F29,0))/C14*100,"")

Sheet 🔑 GSC_Keywords
A1: PIL Perú — Top Keywords Google Search Console (Top 20 por mes)
A2: Ingresa hasta 20 keywords por mes · Azul = ingreso manual · Usa el filtro de Año y Mes para navegar
A3: Año | B3: Mes | C3: Consulta de Búsqueda | D3: Clics | E3: Impresiones | F3: CTR (%) | G3: Posición Media
A4: ── Enero 2021 ── (ingresa hasta 20 keywords)
A5: 2021 | B5: Enero
A6: 2021 | B6: Enero
A7: 2021 | B7: Enero
A8: 2021 | B8: Enero
A9: 2021 | B9: Enero
A10: 2021 | B10: Enero
A11: 2021 | B11: Enero
A12: 2021 | B12: Enero
A13: 2021 | B13: Enero
A14: 2021 | B14: Enero
A15: 2021 | B15: Enero
A16: 2021 | B16: Enero
... A24: 2021 | B24: Enero
A25: ── Febrero 2021 ── (ingresa hasta 20 keywords)
A26: 2021 | B26: Febrero
A27: 2021 | B27: Febrero
A28: 2021 | B28: Febrero
A29: 2021 | B29: Febrero
A30: 2021 | B30: Febrero
A31: 2021 | B31: Febrero
A32: 2021 | B32: Febrero
A33: 2021 | B33: Febrero
A34: 2021 | B34: Febrero
A35: 2021 | B35: Febrero
A36: 2021 | B36: Febrero
A37: 2021 | B37: Febrero
... A45: 2021 | B45: Febrero
A46: ── Marzo 2021 ── (ingresa hasta 20 keywords)
A47: 2021 | B47: Marzo
A48: 2021 | B48: Marzo
A49: 2021 | B49: Marzo
A50: 2021 | B50: Marzo
A51: 2021 | B51: Marzo
A52: 2021 | B52: Marzo
A53: 2021 | B53: Marzo
A54: 2021 | B54: Marzo
A55: 2021 | B55: Marzo
A56: 2021 | B56: Marzo
A57: 2021 | B57: Marzo
A58: 2021 | B58: Marzo
... A66: 2021 | B66: Marzo
A67: ── Abril 2021 ── (ingresa hasta 20 keywords)
A68: 2021 | B68: Abril
A69: 2021 | B69: Abril
A70: 2021 | B70: Abril
A71: 2021 | B71: Abril
A72: 2021 | B72: Abril
A73: 2021 | B73: Abril
A74: 2021 | B74: Abril
A75: 2021 | B75: Abril
A76: 2021 | B76: Abril
A77: 2021 | B77: Abril
A78: 2021 | B78: Abril
A79: 2021 | B79: Abril
... A87: 2021 | B87: Abril
A88: ── Mayo 2021 ── (ingresa hasta 20 keywords)
A89: 2021 | B89: Mayo
A90: 2021 | B90: Mayo
A91: 2021 | B91: Mayo
A92: 2021 | B92: Mayo
A93: 2021 | B93: Mayo
A94: 2021 | B94: Mayo
A95: 2021 | B95: Mayo
A96: 2021 | B96: Mayo
A97: 2021 | B97: Mayo
A98: 2021 | B98: Mayo
A99: 2021 | B99: Mayo
A100: 2021 | B100: Mayo
... A108: 2021 | B108: Mayo
A109: ── Junio 2021 ── (ingresa hasta 20 keywords)
A110: 2021 | B110: Junio
A111: 2021 | B111: Junio
A112: 2021 | B112: Junio
A113: 2021 | B113: Junio
A114: 2021 | B114: Junio
A115: 2021 | B115: Junio
A116: 2021 | B116: Junio
A117: 2021 | B117: Junio
A118: 2021 | B118: Junio
A119: 2021 | B119: Junio
A120: 2021 | B120: Junio
A121: 2021 | B121: Junio
... A129: 2021 | B129: Junio
A130: ── Julio 2021 ── (ingresa hasta 20 keywords)
A131: 2021 | B131: Julio
A132: 2021 | B132: Julio
A133: 2021 | B133: Julio
A134: 2021 | B134: Julio
A135: 2021 | B135: Julio
A136: 2021 | B136: Julio
A137: 2021 | B137: Julio
A138: 2021 | B138: Julio
A139: 2021 | B139: Julio
A140: 2021 | B140: Julio
A141: 2021 | B141: Julio
A142: 2021 | B142: Julio
...

Sheet 📈 Resumen_Ejecutivo
A1: PIL Perú — Resumen Ejecutivo de KPIs | AppSheet-ready · No editar manualmente
A2: Esta hoja consolida automáticamente los datos de las otras hojas. AppSheet leerá directamente desde aquí.
A3: ID_Registro | B3: Año | C3: Mes | D3: Plataforma | E3: Seguidores | F3: Impresiones | G3: Alcance | H3: Interacciones | I3: Nuevos_Seg | J3: Posts | K3: Pct_Alcance | L3: Pct_Interaccion | M3: Estado_Alcance | N3: Estado_Interaccion
A4: 2021_Ene_Fa | B4: 2021 | C4: Enero | D4: Facebook | E4: ='📘 Facebook_KPIs'!C4 -> 0 | F4: ='📘 Facebook_KPIs'!D4 -> 0 | G4: ='📘 Facebook_KPIs'!E4 -> 2366 | H4: ='📘 Facebook_KPIs'!F4 -> 166 | I4: ='📘 Facebook_KPIs'!G4 -> 20 | J4: ='📘 Facebook_KPIs'!H4 -> 7 | K4: ='📘 Facebook_KPIs'!I4 -> 0 | L4: ='📘 Facebook_KPIs'!J4 -> 0.070160609 | ... N4: ='📘 Facebook_KPIs'!L4 -> ✗ Por debajo
A5: 2021_Feb_Fa | B5: 2021 | C5: Febrero | D5: Facebook | E5: ='📘 Facebook_KPIs'!C5 -> 0 | F5: ='📘 Facebook_KPIs'!D5 -> 0 | G5: ='📘 Facebook_KPIs'!E5 -> 917 | H5: ='📘 Facebook_KPIs'!F5 -> 49 | I5: ='📘 Facebook_KPIs'!G5 -> 10 | J5: ='📘 Facebook_KPIs'!H5 -> 1 | K5: ='📘 Facebook_KPIs'!I5 -> 0 | L5: ='📘 Facebook_KPIs'!J5 -> 0.053435115 | ... N5: ='📘 Facebook_KPIs'!L5 -> ✗ Por debajo
A6: 2021_Mar_Fa | B6: 2021 | C6: Marzo | D6: Facebook | E6: ='📘 Facebook_KPIs'!C6 -> 0 | F6: ='📘 Facebook_KPIs'!D6 -> 0 | G6: ='📘 Facebook_KPIs'!E6 -> 2918 | H6: ='📘 Facebook_KPIs'!F6 -> 258 | I6: ='📘 Facebook_KPIs'!G6 -> 15 | J6: ='📘 Facebook_KPIs'!H6 -> 5 | K6: ='📘 Facebook_KPIs'!I6 -> 0 | L6: ='📘 Facebook_KPIs'!J6 -> 0.088416724 | ... N6: ='📘 Facebook_KPIs'!L6 -> ✓ Cumple
A7: 2021_Abr_Fa | B7: 2021 | C7: Abril | D7: Facebook | E7: ='📘 Facebook_KPIs'!C7 -> 0 | F7: ='📘 Facebook_KPIs'!D7 -> 0 | G7: ='📘 Facebook_KPIs'!E7 -> 10771 | H7: ='📘 Facebook_KPIs'!F7 -> 618 | I7: ='📘 Facebook_KPIs'!G7 -> 25 | J7: ='📘 Facebook_KPIs'!H7 -> 9 | K7: ='📘 Facebook_KPIs'!I7 -> 0 | L7: ='📘 Facebook_KPIs'!J7 -> 0.057376288 | ... N7: ='📘 Facebook_KPIs'!L7 -> ✗ Por debajo
A8: 2021_May_Fa | B8: 2021 | C8: Mayo | D8: Facebook | E8: ='📘 Facebook_KPIs'!C8 -> 0 | F8: ='📘 Facebook_KPIs'!D8 -> 0 | G8: ='📘 Facebook_KPIs'!E8 -> 7737 | H8: ='📘 Facebook_KPIs'!F8 -> 633 | I8: ='📘 Facebook_KPIs'!G8 -> 18 | J8: ='📘 Facebook_KPIs'!H8 -> 11 | K8: ='📘 Facebook_KPIs'!I8 -> 0 | L8: ='📘 Facebook_KPIs'!J8 -> 0.081814657 | ... N8: ='📘 Facebook_KPIs'!L8 -> ✓ Cumple
A9: 2021_Jun_Fa | B9: 2021 | C9: Junio | D9: Facebook | E9: ='📘 Facebook_KPIs'!C9 -> 0 | F9: ='📘 Facebook_KPIs'!D9 -> 0 | G9: ='📘 Facebook_KPIs'!E9 -> 6680 | H9: ='📘 Facebook_KPIs'!F9 -> 536 | I9: ='📘 Facebook_KPIs'!G9 -> 15 | J9: ='📘 Facebook_KPIs'!H9 -> 11 | K9: ='📘 Facebook_KPIs'!I9 -> 0 | L9: ='📘 Facebook_KPIs'!J9 -> 0.080239521 | ... N9: ='📘 Facebook_KPIs'!L9 -> ✓ Cumple
A10: 2021_Jul_Fa | B10: 2021 | C10: Julio | D10: Facebook | E10: ='📘 Facebook_KPIs'!C10 -> 0 | F10: ='📘 Facebook_KPIs'!D10 -> 0 | G10: ='📘 Facebook_KPIs'!E10 -> 2182 | H10: ='📘 Facebook_KPIs'!F10 -> 125 | I10: ='📘 Facebook_KPIs'!G10 -> 8 | J10: ='📘 Facebook_KPIs'!H10 -> 3 | K10: ='📘 Facebook_KPIs'!I10 -> 0 | L10: ='📘 Facebook_KPIs'!J10 -> 0.057286893 | ... N10: ='📘 Facebook_KPIs'!L10 -> ✗ Por debajo
A11: 2021_Ago_Fa | B11: 2021 | C11: Agosto | D11: Facebook | E11: ='📘 Facebook_KPIs'!C11 -> 0 | F11: ='📘 Facebook_KPIs'!D11 -> 0 | G11: ='📘 Facebook_KPIs'!E11 -> 782 | H11: ='📘 Facebook_KPIs'!F11 -> 68 | I11: ='📘 Facebook_KPIs'!G11 -> 5 | J11: ='📘 Facebook_KPIs'!H11 -> 1 | K11: ='📘 Facebook_KPIs'!I11 -> 0 | L11: ='📘 Facebook_KPIs'!J11 -> 0.086956522 | ... N11: ='📘 Facebook_KPIs'!L11 -> ✓ Cumple
A12: 2021_Set_Fa | B12: 2021 | C12: Setiembre | D12: Facebook | E12: ='📘 Facebook_KPIs'!C12 -> 0 | F12: ='📘 Facebook_KPIs'!D12 -> 0 | G12: ='📘 Facebook_KPIs'!E12 -> 2302 | H12: ='📘 Facebook_KPIs'!F12 -> 141 | I12: ='📘 Facebook_KPIs'!G12 -> 8 | J12: ='📘 Facebook_KPIs'!H12 -> 3 | K12: ='📘 Facebook_KPIs'!I12 -> 0 | L12: ='📘 Facebook_KPIs'!J12 -> 0.061251086 | ... N12: ='📘 Facebook_KPIs'!L12 -> ✗ Por debajo
A13: 2021_Oct_Fa | B13: 2021 | C13: Octubre | D13: Facebook | E13: ='📘 Facebook_KPIs'!C13 -> 0 | F13: ='📘 Facebook_KPIs'!D13 -> 0 | G13: ='📘 Facebook_KPIs'!E13 -> 4109 | H13: ='📘 Facebook_KPIs'!F13 -> 282 | I13: ='📘 Facebook_KPIs'!G13 -> 12 | J13: ='📘 Facebook_KPIs'!H13 -> 7 | K13: ='📘 Facebook_KPIs'!I13 -> 0 | L13: ='📘 Facebook_KPIs'!J13 -> 0.068629837 | ... N13: ='📘 Facebook_KPIs'!L13 -> ✗ Por debajo
A14: 2021_Nov_Fa | B14: 2021 | C14: Noviembre | D14: Facebook | E14: ='📘 Facebook_KPIs'!C14 -> 0 | F14: ='📘 Facebook_KPIs'!D14 -> 0 | G14: ='📘 Facebook_KPIs'!E14 -> 1748 | H14: ='📘 Facebook_KPIs'!F14 -> 122 | I14: ='📘 Facebook_KPIs'!G14 -> 8 | J14: ='📘 Facebook_KPIs'!H14 -> 5 | K14: ='📘 Facebook_KPIs'!I14 -> 0 | L14: ='📘 Facebook_KPIs'!J14 -> 0.06979405 | ... N14: ='📘 Facebook_KPIs'!L14 -> ✗ Por debajo
A15: 2021_Dic_Fa | B15: 2021 | C15: Diciembre | D15: Facebook | E15: ='📘 Facebook_KPIs'!C15 -> 0 | F15: ='📘 Facebook_KPIs'!D15 -> 0 | G15: ='📘 Facebook_KPIs'!E15 -> 3016 | H15: ='📘 Facebook_KPIs'!F15 -> 316 | I15: ='📘 Facebook_KPIs'!G15 -> 10 | J15: ='📘 Facebook_KPIs'!H15 -> 6 | K15: ='📘 Facebook_KPIs'!I15 -> 0 | L15: ='📘 Facebook_KPIs'!J15 -> 0.10477454 | ... N15: ='📘 Facebook_KPIs'!L15 -> ✓ Cumple
... A75: 2026_Dic_Fa | B75: 2026 | C75: Diciembre | D75: Facebook | E75: ='📘 Facebook_KPIs'!C75 -> 0 | F75: ='📘 Facebook_KPIs'!D75 -> 0 | G75: ='📘 Facebook_KPIs'!E75 -> 0 | H75: ='📘 Facebook_KPIs'!F75 -> 0 | I75: ='📘 Facebook_KPIs'!G75 -> 0 | J75: ='📘 Facebook_KPIs'!H75 -> 0 | K75: ='📘 Facebook_KPIs'!I75 | L75: ='📘 Facebook_KPIs'!J75 | ... N75: ='📘 Facebook_KPIs'!L75
A76: 2022_Ene_Li | B76: 2022 | C76: Enero | D76: LinkedIn | E76: ='💼 LinkedIn_KPIs'!C4 -> 3115 | F76: ='💼 LinkedIn_KPIs'!D4 -> 6054 | G76: ='💼 LinkedIn_KPIs'!E4 -> 695 | H76: ='💼 LinkedIn_KPIs'!F4 -> 339 | I76: ='💼 LinkedIn_KPIs'!G4 -> 27 | J76: ='💼 LinkedIn_KPIs'!H4 -> 5 | K76: ='💼 LinkedIn_KPIs'!I4 -> 0.22311396 | L76: ='💼 LinkedIn_KPIs'!J4 -> 0.055996036 | ... N76: ='💼 LinkedIn_KPIs'!L4 -> ✗ Por debajo
A77: 2022_Feb_Li | B77: 2022 | C77: Febrero | D77: LinkedIn | E77: ='💼 LinkedIn_KPIs'!C5 -> 3152 | F77: ='💼 LinkedIn_KPIs'!D5 -> 6240 | G77: ='💼 LinkedIn_KPIs'!E5 -> 1923 | H77: ='💼 LinkedIn_KPIs'!F5 -> 601 | I77: ='💼 LinkedIn_KPIs'!G5 -> 35 | J77: ='💼 LinkedIn_KPIs'!H5 -> 3 | K77: ='💼 LinkedIn_KPIs'!I5 -> 0.61008883 | L77: ='💼 LinkedIn_KPIs'!J5 -> 0.096314103 | ... N77: ='💼 LinkedIn_KPIs'!L5 -> ✓ Cumple
A78: 2022_Mar_Li | B78: 2022 | C78: Marzo | D78: LinkedIn | E78: ='💼 LinkedIn_KPIs'!C6 -> 3194 | F78: ='💼 LinkedIn_KPIs'!D6 -> 5635 | G78: ='💼 LinkedIn_KPIs'!E6 -> 3330 | H78: ='💼 LinkedIn_KPIs'!F6 -> 488 | I78: ='💼 LinkedIn_KPIs'!G6 -> 42 | J78: ='💼 LinkedIn_KPIs'!H6 -> 2 | K78: ='💼 LinkedIn_KPIs'!I6 -> 1.0425798 | L78: ='💼 LinkedIn_KPIs'!J6 -> 0.086601597 | ... N78: ='💼 LinkedIn_KPIs'!L6 -> ✓ Cumple
A79: 2022_Abr_Li | B79: 2022 | C79: Abril | D79: LinkedIn | E79: ='💼 LinkedIn_KPIs'!C7 -> 3232 | F79: ='💼 LinkedIn_KPIs'!D7 -> 2814 | G79: ='💼 LinkedIn_KPIs'!E7 -> 559 | H79: ='💼 LinkedIn_KPIs'!F7 -> 349 | I79: ='💼 LinkedIn_KPIs'!G7 -> 29 | J79: ='💼 LinkedIn_KPIs'!H7 -> 3 | K79: ='💼 LinkedIn_KPIs'!I7 -> 0.17295792 | L79: ='💼 LinkedIn_KPIs'!J7 -> 0.12402274 | ... N79: ='💼 LinkedIn_KPIs'!L7 -> ✓ Cumple
A80: 2022_May_Li | B80: 2022 | C80: Mayo | D80: LinkedIn | E80: ='💼 LinkedIn_KPIs'!C8 -> 3273 | F80: ='💼 LinkedIn_KPIs'!D8 -> 4634 | G80: ='💼 LinkedIn_KPIs'!E8 -> 718 | H80: ='💼 LinkedIn_KPIs'!F8 -> 341 | I80: ='💼 LinkedIn_KPIs'!G8 -> 41 | J80: ='💼 LinkedIn_KPIs'!H8 -> 4 | K80: ='💼 LinkedIn_KPIs'!I8 -> 0.21937061 | L80: ='💼 LinkedIn_KPIs'!J8 -> 0.073586534 | ... N80: ='💼 LinkedIn_KPIs'!L8 -> ✗ Por debajo
A81: 2022_Jun_Li | B81: 2022 | C81: Junio | D81: LinkedIn | E81: ='💼 LinkedIn_KPIs'!C9 -> 3304 | F81: ='💼 LinkedIn_KPIs'!D9 -> 3752 | G81: ='💼 LinkedIn_KPIs'!E9 -> 429 | H81: ='💼 LinkedIn_KPIs'!F9 -> 152 | I81: ='💼 LinkedIn_KPIs'!G9 -> 32 | J81: ='💼 LinkedIn_KPIs'!H9 -> 5 | K81: ='💼 LinkedIn_KPIs'!I9 -> 0.12984262 | L81: ='💼 LinkedIn_KPIs'!J9 -> 0.040511727 | ... N81: ='💼 LinkedIn_KPIs'!L9 -> ✗ Por debajo
A82: 2022_Jul_Li | B82: 2022 | C82: Julio | D82: LinkedIn | E82: ='💼 LinkedIn_KPIs'!C10 -> 3314 | F82: ='💼 LinkedIn_KPIs'!D10 -> 4884 | G82: ='💼 LinkedIn_KPIs'!E10 -> 975 | H82: ='💼 LinkedIn_KPIs'!F10 -> 198 | I82: ='💼 LinkedIn_KPIs'!G10 -> 26 | J82: ='💼 LinkedIn_KPIs'!H10 -> 3 | K82: ='💼 LinkedIn_KPIs'!I10 -> 0.2942064 | L82: ='💼 LinkedIn_KPIs'!J10 -> 0.040540541 | ... N82: ='💼 LinkedIn_KPIs'!L10 -> ✗ Por debajo
A83: 2022_Ago_Li | B83: 2022 | C83: Agosto | D83: LinkedIn | E83: ='💼 LinkedIn_KPIs'!C11 -> 3348 | F83: ='💼 LinkedIn_KPIs'!D11 -> 5385 | G83: ='💼 LinkedIn_KPIs'!E11 -> 665 | H83: ='💼 LinkedIn_KPIs'!F11 -> 367 | I83: ='💼 LinkedIn_KPIs'!G11 -> 34 | J83: ='💼 LinkedIn_KPIs'!H11 -> 5 | K83: ='💼 LinkedIn_KPIs'!I11 -> 0.19862605 | L83: ='💼 LinkedIn_KPIs'!J11 -> 0.068152275 | ... N83: ='💼 LinkedIn_KPIs'!L11 -> ✗ Por debajo
A84: 2022_Set_Li | B84: 2022 | C84: Setiembre | D84: LinkedIn | E84: ='💼 LinkedIn_KPIs'!C12 -> 3470 | F84: ='💼 LinkedIn_KPIs'!D12 -> 5491 | G84: ='💼 LinkedIn_KPIs'!E12 -> 743 | H84: ='💼 LinkedIn_KPIs'!F12 -> 347 | I84: ='💼 LinkedIn_KPIs'!G12 -> 135 | J84: ='💼 LinkedIn_KPIs'!H12 -> 4 | K84: ='💼 LinkedIn_KPIs'!I12 -> 0.21412104 | L84: ='💼 LinkedIn_KPIs'!J12 -> 0.063194318 | ... N84: ='💼 LinkedIn_KPIs'!L12 -> ✗ Por debajo
A85: 2022_Oct_Li | B85: 2022 | C85: Octubre | D85: LinkedIn | E85: ='💼 LinkedIn_KPIs'!C13 -> 3470 | F85: ='💼 LinkedIn_KPIs'!D13 -> 6408 | G85: ='💼 LinkedIn_KPIs'!E13 -> 1602 | H85: ='💼 LinkedIn_KPIs'!F13 -> 256 | I85: ='💼 LinkedIn_KPIs'!G13 -> 31 | J85: ='💼 LinkedIn_KPIs'!H13 -> 4 | K85: ='💼 LinkedIn_KPIs'!I13 -> 0.46167147 | L85: ='💼 LinkedIn_KPIs'!J13 -> 0.039950062 | ... N85: ='💼 LinkedIn_KPIs'!L13 -> ✗ Por debajo
A86: 2022_Nov_Li | B86: 2022 | C86: Noviembre | D86: LinkedIn | E86: ='💼 LinkedIn_KPIs'!C14 -> 3690 | F86: ='💼 LinkedIn_KPIs'!D14 -> 6406 | G86: ='💼 LinkedIn_KPIs'!E14 -> 1188 | H86: ='💼 LinkedIn_KPIs'!F14 -> 730 | I86: ='💼 LinkedIn_KPIs'!G14 -> 112 | J86: ='💼 LinkedIn_KPIs'!H14 -> 3 | K86: ='💼 LinkedIn_KPIs'!I14 -> 0.32195122 | L86: ='💼 LinkedIn_KPIs'!J14 -> 0.11395567 | ... N86: ='💼 LinkedIn_KPIs'!L14 -> ✓ Cumple
A87: 2022_Dic_Li | B87: 2022 | C87: Diciembre | D87: LinkedIn | E87: ='💼 LinkedIn_KPIs'!C15 -> 3690 | F87: ='💼 LinkedIn_KPIs'!D15 -> 6406 | G87: ='💼 LinkedIn_KPIs'!E15 -> 1188 | H87: ='💼 LinkedIn_KPIs'!F15 -> 730 | I87: ='💼 LinkedIn_KPIs'!G15 -> 112 | J87: ='💼 LinkedIn_KPIs'!H15 -> 2 | K87: ='💼 LinkedIn_KPIs'!I15 -> 0.32195122 | L87: ='💼 LinkedIn_KPIs'!J15 -> 0.11395567 | ... N87: ='💼 LinkedIn_KPIs'!L15 -> ✓ Cumple
... A135: 2026_Dic_Li | B135: 2026 | C135: Diciembre | D135: LinkedIn | E135: ='💼 LinkedIn_KPIs'!C63 -> 0 | F135: ='💼 LinkedIn_KPIs'!D63 -> 0 | G135: ='💼 LinkedIn_KPIs'!E63 -> 0 | H135: ='💼 LinkedIn_KPIs'!F63 -> 0 | I135: ='💼 LinkedIn_KPIs'!G63 -> 0 | J135: ='💼 LinkedIn_KPIs'!H63 -> 0 | K135: ='💼 LinkedIn_KPIs'!I63 | L135: ='💼 LinkedIn_KPIs'!J63 | ... N135: ='💼 LinkedIn_KPIs'!L63
